{
  "area": 12.7872,
  "cell_footprint": "maj3",
  "cell_leakage_power": 0.0,
  "pg_pin VGND": {
    "pg_type": "primary_ground",
    "voltage_name": "VGND"
  },
  "pg_pin VNB": {
    "pg_type": "primary_ground",
    "voltage_name": "VNB"
  },
  "pg_pin VPB": {
    "pg_type": "primary_power",
    "voltage_name": "VPB"
  },
  "pg_pin VPWR": {
    "pg_type": "primary_power",
    "voltage_name": "VPWR"
  },
  "pin A": {
    "capacitance": 0.00567,
    "clock": "false",
    "direction": "input",
    "internal_power": {
      "fall_power hidden_pwr_template13": {
        "index_1": [
          0.01,
          0.01735,
          0.02602,
          0.03903,
          0.05855,
          0.08782,
          0.13172,
          0.19757,
          0.29634,
          0.44449,
          0.6667,
          1.0,
          1.5
        ],
        "values": [
          0.00445,
          0.0042,
          0.00403,
          0.00409,
          0.00397,
          0.00404,
          0.00397,
          0.00401,
          0.00395,
          0.0043,
          0.00433,
          0.00474,
          0.00487
        ]
      },
      "rise_power hidden_pwr_template13": {
        "index_1": [
          0.01,
          0.01735,
          0.02602,
          0.03903,
          0.05855,
          0.08782,
          0.13172,
          0.19757,
          0.29634,
          0.44449,
          0.6667,
          1.0,
          1.5
        ],
        "values": [
          0.00246,
          0.00255,
          0.00275,
          0.00213,
          0.00234,
          0.00225,
          0.00232,
          0.00242,
          0.00245,
          0.00265,
          0.00268,
          0.00291,
          0.00294
        ]
      }
    },
    "max_transition": 1.0,
    "related_ground_pin": "VGND",
    "related_power_pin": "VPWR"
  },
  "pin B": {
    "capacitance": 0.005,
    "clock": "false",
    "direction": "input",
    "internal_power": {
      "fall_power hidden_pwr_template13": {
        "index_1": [
          0.01,
          0.01735,
          0.02602,
          0.03903,
          0.05855,
          0.08782,
          0.13172,
          0.19757,
          0.29634,
          0.44449,
          0.6667,
          1.0,
          1.5
        ],
        "values": [
          0.00264,
          0.00257,
          0.00261,
          0.00269,
          0.00267,
          0.00263,
          0.00269,
          0.00278,
          0.00276,
          0.003,
          0.00301,
          0.00326,
          0.00329
        ]
      },
      "rise_power hidden_pwr_template13": {
        "index_1": [
          0.01,
          0.01735,
          0.02602,
          0.03903,
          0.05855,
          0.08782,
          0.13172,
          0.19757,
          0.29634,
          0.44449,
          0.6667,
          1.0,
          1.5
        ],
        "values": [
          0.00405,
          0.00382,
          0.0038,
          0.0039,
          0.00383,
          0.00387,
          0.00383,
          0.00385,
          0.00386,
          0.0042,
          0.00426,
          0.00469,
          0.00484
        ]
      }
    },
    "max_transition": 1.0,
    "related_ground_pin": "VGND",
    "related_power_pin": "VPWR"
  },
  "pin C": {
    "capacitance": 0.00527,
    "clock": "false",
    "direction": "input",
    "internal_power": {
      "fall_power hidden_pwr_template13": {
        "index_1": [
          0.01,
          0.01735,
          0.02602,
          0.03903,
          0.05855,
          0.08782,
          0.13172,
          0.19757,
          0.29634,
          0.44449,
          0.6667,
          1.0,
          1.5
        ],
        "values": [
          0.00267,
          0.00252,
          0.00282,
          0.00221,
          0.00233,
          0.0022,
          0.00225,
          0.00223,
          0.00232,
          0.0025,
          0.00256,
          0.00281,
          0.0029
        ]
      },
      "rise_power hidden_pwr_template13": {
        "index_1": [
          0.01,
          0.01735,
          0.02602,
          0.03903,
          0.05855,
          0.08782,
          0.13172,
          0.19757,
          0.29634,
          0.44449,
          0.6667,
          1.0,
          1.5
        ],
        "values": [
          0.00325,
          0.00293,
          0.00291,
          0.00297,
          0.00279,
          0.00275,
          0.00276,
          0.00275,
          0.00272,
          0.00295,
          0.00296,
          0.00322,
          0.00329
        ]
      }
    },
    "max_transition": 1.0,
    "related_ground_pin": "VGND",
    "related_power_pin": "VPWR"
  },
  "pin X": {
    "direction": "output",
    "function": "(A&B) | (A&C) | (B&C)",
    "internal_power": [
      {
        "fall_power pwr_template13x6": {
          "index_1": [
            0.01,
            0.01735,
            0.02602,
            0.03903,
            0.05855,
            0.08782,
            0.13172,
            0.19757,
            0.29634,
            0.44449,
            0.6667,
            1.0,
            1.5
          ],
          "index_2": [
            0.0,
            0.00694,
            0.01388,
            0.02775,
            0.05551,
            0.11102
          ],
          "values": [
            [
              0.03277,
              0.02429,
              0.01562,
              -0.00196,
              -0.03739,
              -0.10846
            ],
            [
              0.03269,
              0.0242,
              0.01554,
              -0.00203,
              -0.03747,
              -0.10854
            ],
            [
              0.03266,
              0.02418,
              0.01551,
              -0.00206,
              -0.0375,
              -0.10857
            ],
            [
              0.03259,
              0.02412,
              0.01545,
              -0.00212,
              -0.03755,
              -0.10862
            ],
            [
              0.03255,
              0.02407,
              0.0154,
              -0.00216,
              -0.0376,
              -0.10867
            ],
            [
              0.03249,
              0.02402,
              0.01534,
              -0.00222,
              -0.03766,
              -0.10872
            ],
            [
              0.03243,
              0.02395,
              0.01527,
              -0.00229,
              -0.03772,
              -0.10879
            ],
            [
              0.03237,
              0.02389,
              0.01521,
              -0.00236,
              -0.03779,
              -0.10885
            ],
            [
              0.03231,
              0.02382,
              0.01514,
              -0.00242,
              -0.03785,
              -0.10891
            ],
            [
              0.03227,
              0.02376,
              0.01507,
              -0.00248,
              -0.03789,
              -0.10894
            ],
            [
              0.03221,
              0.02368,
              0.015,
              -0.00255,
              -0.03795,
              -0.10899
            ],
            [
              0.03217,
              0.02361,
              0.01491,
              -0.00262,
              -0.03801,
              -0.10903
            ],
            [
              0.0322,
              0.02354,
              0.01481,
              -0.00271,
              -0.03806,
              -0.10905
            ]
          ]
        },
        "related_pin": "A",
        "rise_power pwr_template13x6": {
          "index_1": [
            0.01,
            0.01735,
            0.02602,
            0.03903,
            0.05855,
            0.08782,
            0.13172,
            0.19757,
            0.29634,
            0.44449,
            0.6667,
            1.0,
            1.5
          ],
          "index_2": [
            0.0,
            0.00694,
            0.01388,
            0.02775,
            0.05551,
            0.11102
          ],
          "values": [
            [
              0.00734,
              0.01647,
              0.02534,
              0.04306,
              0.07824,
              0.14867
            ],
            [
              0.00725,
              0.01638,
              0.02529,
              0.04292,
              0.07814,
              0.1485
            ],
            [
              0.00714,
              0.01628,
              0.02515,
              0.04281,
              0.07802,
              0.14847
            ],
            [
              0.00706,
              0.01618,
              0.02507,
              0.04273,
              0.07805,
              0.14844
            ],
            [
              0.00695,
              0.01606,
              0.02497,
              0.04264,
              0.07791,
              0.14826
            ],
            [
              0.00685,
              0.01598,
              0.02489,
              0.04254,
              0.07776,
              0.14813
            ],
            [
              0.00677,
              0.01589,
              0.0248,
              0.04244,
              0.07769,
              0.14831
            ],
            [
              0.00666,
              0.01578,
              0.02469,
              0.04243,
              0.07759,
              0.14804
            ],
            [
              0.00655,
              0.01566,
              0.02456,
              0.04224,
              0.07768,
              0.14814
            ],
            [
              0.00644,
              0.01553,
              0.02443,
              0.04214,
              0.07748,
              0.14806
            ],
            [
              0.00635,
              0.01539,
              0.0243,
              0.04196,
              0.0773,
              0.14772
            ],
            [
              0.00626,
              0.01532,
              0.02422,
              0.04189,
              0.07732,
              0.14775
            ],
            [
              0.00621,
              0.01523,
              0.02419,
              0.04187,
              0.07718,
              0.1478
            ]
          ]
        },
        "when": "(B&!C) | (!B&C)"
      },
      {
        "fall_power pwr_template13x6": {
          "index_1": [
            0.01,
            0.01735,
            0.02602,
            0.03903,
            0.05855,
            0.08782,
            0.13172,
            0.19757,
            0.29634,
            0.44449,
            0.6667,
            1.0,
            1.5
          ],
          "index_2": [
            0.0,
            0.00694,
            0.01388,
            0.02775,
            0.05551,
            0.11102
          ],
          "values": [
            [
              0.02627,
              0.01785,
              0.0092,
              -0.00833,
              -0.04373,
              -0.11479
            ],
            [
              0.02616,
              0.01774,
              0.00909,
              -0.00844,
              -0.04384,
              -0.1149
            ],
            [
              0.0261,
              0.01766,
              0.00902,
              -0.00851,
              -0.0439,
              -0.11497
            ],
            [
              0.026,
              0.01755,
              0.0089,
              -0.00863,
              -0.04403,
              -0.11509
            ],
            [
              0.02581,
              0.01737,
              0.00872,
              -0.00881,
              -0.04421,
              -0.11527
            ],
            [
              0.02561,
              0.01717,
              0.00852,
              -0.00901,
              -0.04441,
              -0.11546
            ],
            [
              0.02541,
              0.01695,
              0.00829,
              -0.00924,
              -0.04464,
              -0.11569
            ],
            [
              0.02515,
              0.01672,
              0.00805,
              -0.00947,
              -0.04486,
              -0.11591
            ],
            [
              0.02498,
              0.01651,
              0.00784,
              -0.00968,
              -0.04507,
              -0.11611
            ],
            [
              0.02482,
              0.01632,
              0.00763,
              -0.00989,
              -0.04524,
              -0.11627
            ],
            [
              0.02472,
              0.01617,
              0.00747,
              -0.01004,
              -0.04538,
              -0.11639
            ],
            [
              0.02468,
              0.01608,
              0.00739,
              -0.01012,
              -0.04545,
              -0.11644
            ],
            [
              0.02482,
              0.01611,
              0.00738,
              -0.01013,
              -0.04544,
              -0.1164
            ]
          ]
        },
        "related_pin": "B",
        "rise_power pwr_template13x6": {
          "index_1": [
            0.01,
            0.01735,
            0.02602,
            0.03903,
            0.05855,
            0.08782,
            0.13172,
            0.19757,
            0.29634,
            0.44449,
            0.6667,
            1.0,
            1.5
          ],
          "index_2": [
            0.0,
            0.00694,
            0.01388,
            0.02775,
            0.05551,
            0.11102
          ],
          "values": [
            [
              0.00727,
              0.01646,
              0.0254,
              0.04305,
              0.07828,
              0.14874
            ],
            [
              0.00727,
              0.01647,
              0.02538,
              0.0431,
              0.07826,
              0.14864
            ],
            [
              0.00719,
              0.01639,
              0.02531,
              0.04299,
              0.07822,
              0.14858
            ],
            [
              0.00718,
              0.01637,
              0.02531,
              0.04302,
              0.07823,
              0.14864
            ],
            [
              0.00709,
              0.01628,
              0.0252,
              0.04293,
              0.07813,
              0.14857
            ],
            [
              0.00697,
              0.01615,
              0.0251,
              0.0428,
              0.07805,
              0.14858
            ],
            [
              0.00679,
              0.01596,
              0.0249,
              0.04265,
              0.07785,
              0.14841
            ],
            [
              0.00655,
              0.01571,
              0.02464,
              0.04238,
              0.07765,
              0.1481
            ],
            [
              0.00627,
              0.0154,
              0.02434,
              0.04207,
              0.07729,
              0.14792
            ],
            [
              0.00598,
              0.01507,
              0.02398,
              0.04172,
              0.07704,
              0.14751
            ],
            [
              0.00574,
              0.01477,
              0.02366,
              0.04138,
              0.07672,
              0.14722
            ],
            [
              0.00554,
              0.01459,
              0.02349,
              0.04114,
              0.07646,
              0.14723
            ],
            [
              0.00546,
              0.01443,
              0.0234,
              0.04109,
              0.07641,
              0.14668
            ]
          ]
        },
        "when": "(A&!C) | (!A&C)"
      },
      {
        "fall_power pwr_template13x6": {
          "index_1": [
            0.01,
            0.01735,
            0.02602,
            0.03903,
            0.05855,
            0.08782,
            0.13172,
            0.19757,
            0.29634,
            0.44449,
            0.6667,
            1.0,
            1.5
          ],
          "index_2": [
            0.0,
            0.00694,
            0.01388,
            0.02775,
            0.05551,
            0.11102
          ],
          "values": [
            [
              0.0297,
              0.02132,
              0.01269,
              -0.00481,
              -0.04018,
              -0.11121
            ],
            [
              0.02966,
              0.02125,
              0.01263,
              -0.00487,
              -0.04024,
              -0.11127
            ],
            [
              0.02959,
              0.02117,
              0.01255,
              -0.00495,
              -0.04033,
              -0.11136
            ],
            [
              0.0295,
              0.02109,
              0.01247,
              -0.00503,
              -0.0404,
              -0.11144
            ],
            [
              0.02939,
              0.02097,
              0.01234,
              -0.00514,
              -0.04052,
              -0.11155
            ],
            [
              0.02925,
              0.02084,
              0.01222,
              -0.00528,
              -0.04066,
              -0.11169
            ],
            [
              0.0291,
              0.02068,
              0.01205,
              -0.00545,
              -0.04082,
              -0.11185
            ],
            [
              0.02894,
              0.02051,
              0.01187,
              -0.00563,
              -0.041,
              -0.11202
            ],
            [
              0.02877,
              0.02035,
              0.0117,
              -0.00579,
              -0.04115,
              -0.11218
            ],
            [
              0.02868,
              0.02019,
              0.01155,
              -0.00595,
              -0.0413,
              -0.1123
            ],
            [
              0.02857,
              0.02006,
              0.0114,
              -0.0061,
              -0.04142,
              -0.11242
            ],
            [
              0.02853,
              0.01998,
              0.01131,
              -0.00619,
              -0.04151,
              -0.11248
            ],
            [
              0.02861,
              0.01996,
              0.01124,
              -0.00624,
              -0.04154,
              -0.11248
            ]
          ]
        },
        "related_pin": "C",
        "rise_power pwr_template13x6": {
          "index_1": [
            0.01,
            0.01735,
            0.02602,
            0.03903,
            0.05855,
            0.08782,
            0.13172,
            0.19757,
            0.29634,
            0.44449,
            0.6667,
            1.0,
            1.5
          ],
          "index_2": [
            0.0,
            0.00694,
            0.01388,
            0.02775,
            0.05551,
            0.11102
          ],
          "values": [
            [
              0.00735,
              0.01661,
              0.02562,
              0.04336,
              0.0787,
              0.14922
            ],
            [
              0.00727,
              0.01654,
              0.02553,
              0.04331,
              0.07867,
              0.14903
            ],
            [
              0.00718,
              0.01644,
              0.02545,
              0.04322,
              0.0785,
              0.14902
            ],
            [
              0.00716,
              0.01643,
              0.02542,
              0.04324,
              0.07853,
              0.14895
            ],
            [
              0.00705,
              0.01631,
              0.02533,
              0.04306,
              0.07853,
              0.14905
            ],
            [
              0.00694,
              0.01617,
              0.02518,
              0.04295,
              0.07838,
              0.14876
            ],
            [
              0.00678,
              0.01603,
              0.02501,
              0.04286,
              0.0781,
              0.14861
            ],
            [
              0.00659,
              0.01581,
              0.0248,
              0.04257,
              0.0779,
              0.14843
            ],
            [
              0.00637,
              0.01556,
              0.02456,
              0.04232,
              0.07774,
              0.14819
            ],
            [
              0.00614,
              0.0153,
              0.02428,
              0.04201,
              0.07744,
              0.14796
            ],
            [
              0.00593,
              0.01501,
              0.02398,
              0.04175,
              0.07715,
              0.14775
            ],
            [
              0.00576,
              0.01485,
              0.02378,
              0.04153,
              0.07691,
              0.14769
            ],
            [
              0.00567,
              0.0147,
              0.02369,
              0.04143,
              0.07673,
              0.14721
            ]
          ]
        },
        "when": "(A&!B) | (!A&B)"
      }
    ],
    "max_capacitance": 0.07318,
    "power_down_function": "(!VPWR + VGND)",
    "related_ground_pin": "VGND",
    "related_power_pin": "VPWR",
    "timing": [
      {
        "cell_fall delay_template13x6": {
          "index_1": [
            0.01,
            0.01735,
            0.02602,
            0.03903,
            0.05855,
            0.08782,
            0.13172,
            0.19757,
            0.29634,
            0.44449,
            0.6667,
            1.0,
            1.5
          ],
          "index_2": [
            0.0,
            0.00694,
            0.01388,
            0.02775,
            0.05551,
            0.11102
          ],
          "values": [
            [
              0.34968,
              0.4444,
              0.50596,
              0.6005,
              0.75712,
              1.04177
            ],
            [
              0.35211,
              0.44685,
              0.50838,
              0.60292,
              0.75954,
              1.04424
            ],
            [
              0.35561,
              0.45033,
              0.51188,
              0.60643,
              0.76303,
              1.04762
            ],
            [
              0.36124,
              0.45598,
              0.51753,
              0.61209,
              0.7687,
              1.05327
            ],
            [
              0.37004,
              0.46476,
              0.52635,
              0.62091,
              0.77749,
              1.06211
            ],
            [
              0.38318,
              0.47789,
              0.53947,
              0.63405,
              0.79065,
              1.07532
            ],
            [
              0.40221,
              0.4969,
              0.55848,
              0.65307,
              0.80969,
              1.09433
            ],
            [
              0.42972,
              0.52435,
              0.58596,
              0.68057,
              0.83726,
              1.12176
            ],
            [
              0.47024,
              0.56481,
              0.62638,
              0.72103,
              0.87775,
              1.16235
            ],
            [
              0.53048,
              0.62492,
              0.68649,
              0.78129,
              0.93799,
              1.22269
            ],
            [
              0.61982,
              0.71432,
              0.77612,
              0.87092,
              1.02782,
              1.31232
            ],
            [
              0.74147,
              0.84107,
              0.90447,
              1.00047,
              1.15797,
              1.44297
            ],
            [
              0.9005,
              1.0077,
              1.0755,
              1.1762,
              1.3373,
              1.6237
            ]
          ]
        },
        "cell_rise delay_template13x6": {
          "index_1": [
            0.01,
            0.01735,
            0.02602,
            0.03903,
            0.05855,
            0.08782,
            0.13172,
            0.19757,
            0.29634,
            0.44449,
            0.6667,
            1.0,
            1.5
          ],
          "index_2": [
            0.0,
            0.00694,
            0.01388,
            0.02775,
            0.05551,
            0.11102
          ],
          "values": [
            [
              0.20115,
              0.28667,
              0.35627,
              0.49006,
              0.75533,
              1.28317
            ],
            [
              0.20407,
              0.28947,
              0.35926,
              0.49304,
              0.75821,
              1.28604
            ],
            [
              0.20772,
              0.29318,
              0.3628,
              0.4966,
              0.76125,
              1.28992
            ],
            [
              0.21305,
              0.29842,
              0.36813,
              0.50196,
              0.76658,
              1.29478
            ],
            [
              0.22069,
              0.30606,
              0.37575,
              0.50959,
              0.77386,
              1.30261
            ],
            [
              0.23175,
              0.31707,
              0.38681,
              0.52056,
              0.78558,
              1.31322
            ],
            [
              0.24808,
              0.3334,
              0.40298,
              0.53667,
              0.80178,
              1.32923
            ],
            [
              0.27242,
              0.35768,
              0.42721,
              0.56097,
              0.82587,
              1.35296
            ],
            [
              0.30874,
              0.39382,
              0.46332,
              0.59737,
              0.86195,
              1.39045
            ],
            [
              0.36042,
              0.44638,
              0.51596,
              0.64979,
              0.91539,
              1.44289
            ],
            [
              0.42826,
              0.51702,
              0.58702,
              0.72132,
              0.98672,
              1.51452
            ],
            [
              0.51557,
              0.60787,
              0.67887,
              0.81367,
              1.07897,
              1.60617
            ],
            [
              0.6251,
              0.7226,
              0.7948,
              0.9299,
              1.1961,
              1.7237
            ]
          ]
        },
        "fall_transition delay_template13x6": {
          "index_1": [
            0.01,
            0.01735,
            0.02602,
            0.03903,
            0.05855,
            0.08782,
            0.13172,
            0.19757,
            0.29634,
            0.44449,
            0.6667,
            1.0,
            1.5
          ],
          "index_2": [
            0.0,
            0.00694,
            0.01388,
            0.02775,
            0.05551,
            0.11102
          ],
          "values": [
            [
              0.04952,
              0.12203,
              0.17098,
              0.25632,
              0.42379,
              0.77442
            ],
            [
              0.04953,
              0.12201,
              0.17066,
              0.25547,
              0.42383,
              0.77513
            ],
            [
              0.04951,
              0.12203,
              0.17067,
              0.2563,
              0.42396,
              0.77432
            ],
            [
              0.0495,
              0.12203,
              0.1706,
              0.25629,
              0.42375,
              0.77431
            ],
            [
              0.04952,
              0.1218,
              0.17071,
              0.25592,
              0.42484,
              0.77432
            ],
            [
              0.04952,
              0.12203,
              0.17066,
              0.25628,
              0.42361,
              0.77428
            ],
            [
              0.04951,
              0.12204,
              0.17067,
              0.25628,
              0.42358,
              0.77425
            ],
            [
              0.04949,
              0.12181,
              0.17084,
              0.25548,
              0.42382,
              0.77498
            ],
            [
              0.04952,
              0.12186,
              0.17072,
              0.2554,
              0.4238,
              0.7751
            ],
            [
              0.04955,
              0.1219,
              0.17086,
              0.2555,
              0.4236,
              0.7751
            ],
            [
              0.0502,
              0.1223,
              0.1712,
              0.2565,
              0.424,
              0.7746
            ],
            [
              0.055,
              0.1276,
              0.1755,
              0.2583,
              0.4253,
              0.7756
            ],
            [
              0.0613,
              0.1377,
              0.1869,
              0.2689,
              0.4327,
              0.7784
            ]
          ]
        },
        "related_pin": "A",
        "rise_transition delay_template13x6": {
          "index_1": [
            0.01,
            0.01735,
            0.02602,
            0.03903,
            0.05855,
            0.08782,
            0.13172,
            0.19757,
            0.29634,
            0.44449,
            0.6667,
            1.0,
            1.5
          ],
          "index_2": [
            0.0,
            0.00694,
            0.01388,
            0.02775,
            0.05551,
            0.11102
          ],
          "values": [
            [
              0.03942,
              0.12733,
              0.21575,
              0.39691,
              0.76531,
              1.5025
            ],
            [
              0.03942,
              0.12719,
              0.21543,
              0.39712,
              0.76474,
              1.50238
            ],
            [
              0.03942,
              0.12713,
              0.21557,
              0.39673,
              0.76491,
              1.5007
            ],
            [
              0.03938,
              0.12707,
              0.21538,
              0.39693,
              0.76415,
              1.50249
            ],
            [
              0.03937,
              0.12705,
              0.21537,
              0.39683,
              0.76443,
              1.50208
            ],
            [
              0.0394,
              0.12709,
              0.21527,
              0.39687,
              0.76422,
              1.50191
            ],
            [
              0.03942,
              0.12717,
              0.21542,
              0.39651,
              0.76473,
              1.50162
            ],
            [
              0.03941,
              0.12713,
              0.21555,
              0.39663,
              0.7647,
              1.50075
            ],
            [
              0.03939,
              0.12718,
              0.21553,
              0.39684,
              0.76405,
              1.50068
            ],
            [
              0.04092,
              0.12777,
              0.21569,
              0.39652,
              0.76488,
              1.5011
            ],
            [
              0.04351,
              0.1301,
              0.2171,
              0.3975,
              0.7638,
              1.5021
            ],
            [
              0.0473,
              0.1333,
              0.2195,
              0.3981,
              0.7655,
              1.5016
            ],
            [
              0.0529,
              0.1377,
              0.2226,
              0.4004,
              0.7643,
              1.5025
            ]
          ]
        },
        "sdf_cond": "(!B&C)",
        "timing_sense": "positive_unate",
        "when": "(!B&C)"
      },
      {
        "cell_fall delay_template13x6": {
          "index_1": [
            0.01,
            0.01735,
            0.02602,
            0.03903,
            0.05855,
            0.08782,
            0.13172,
            0.19757,
            0.29634,
            0.44449,
            0.6667,
            1.0,
            1.5
          ],
          "index_2": [
            0.0,
            0.00694,
            0.01388,
            0.02775,
            0.05551,
            0.11102
          ],
          "values": [
            [
              0.3585,
              0.43831,
              0.48991,
              0.57421,
              0.72214,
              1.00237
            ],
            [
              0.36142,
              0.44122,
              0.49283,
              0.5771,
              0.72513,
              1.00514
            ],
            [
              0.36519,
              0.44502,
              0.49661,
              0.5809,
              0.72878,
              1.00902
            ],
            [
              0.37111,
              0.45093,
              0.50253,
              0.58681,
              0.73484,
              1.01497
            ],
            [
              0.38016,
              0.45998,
              0.51159,
              0.59587,
              0.74389,
              1.02401
            ],
            [
              0.39351,
              0.4733,
              0.52492,
              0.60921,
              0.75724,
              1.03732
            ],
            [
              0.41274,
              0.49251,
              0.54411,
              0.62842,
              0.7764,
              1.05663
            ],
            [
              0.44056,
              0.52031,
              0.5719,
              0.65623,
              0.80413,
              1.08436
            ],
            [
              0.48164,
              0.56132,
              0.6129,
              0.69724,
              0.84525,
              1.12555
            ],
            [
              0.5429,
              0.62248,
              0.67409,
              0.75839,
              0.90649,
              1.18659
            ],
            [
              0.63442,
              0.71392,
              0.76552,
              0.84992,
              0.99802,
              1.27822
            ],
            [
              0.76197,
              0.84537,
              0.89797,
              0.98317,
              1.13167,
              1.41197
            ],
            [
              0.929,
              1.0189,
              1.0746,
              1.1632,
              1.3143,
              1.5959
            ]
          ]
        },
        "cell_rise delay_template13x6": {
          "index_1": [
            0.01,
            0.01735,
            0.02602,
            0.03903,
            0.05855,
            0.08782,
            0.13172,
            0.19757,
            0.29634,
            0.44449,
            0.6667,
            1.0,
            1.5
          ],
          "index_2": [
            0.0,
            0.00694,
            0.01388,
            0.02775,
            0.05551,
            0.11102
          ],
          "values": [
            [
              0.1861,
              0.2741,
              0.3433,
              0.47576,
              0.73924,
              1.26617
            ],
            [
              0.18876,
              0.27673,
              0.34592,
              0.47836,
              0.7418,
              1.26874
            ],
            [
              0.19219,
              0.28015,
              0.34933,
              0.48176,
              0.74462,
              1.27242
            ],
            [
              0.1975,
              0.28545,
              0.35468,
              0.48705,
              0.75048,
              1.27758
            ],
            [
              0.20509,
              0.29303,
              0.36228,
              0.4946,
              0.75814,
              1.28321
            ],
            [
              0.21617,
              0.3041,
              0.37334,
              0.50583,
              0.7687,
              1.29632
            ],
            [
              0.23258,
              0.32047,
              0.38976,
              0.52231,
              0.78557,
              1.31293
            ],
            [
              0.2571,
              0.34497,
              0.41433,
              0.54694,
              0.80989,
              1.33566
            ],
            [
              0.29331,
              0.38132,
              0.45072,
              0.58334,
              0.84725,
              1.37325
            ],
            [
              0.34332,
              0.43323,
              0.50283,
              0.63589,
              0.89959,
              1.42489
            ],
            [
              0.40823,
              0.50202,
              0.57262,
              0.70602,
              0.97002,
              1.49652
            ],
            [
              0.49077,
              0.58997,
              0.66197,
              0.79627,
              1.06027,
              1.58587
            ],
            [
              0.5927,
              0.7,
              0.7737,
              0.9089,
              1.1735,
              1.7002
            ]
          ]
        },
        "fall_transition delay_template13x6": {
          "index_1": [
            0.01,
            0.01735,
            0.02602,
            0.03903,
            0.05855,
            0.08782,
            0.13172,
            0.19757,
            0.29634,
            0.44449,
            0.6667,
            1.0,
            1.5
          ],
          "index_2": [
            0.0,
            0.00694,
            0.01388,
            0.02775,
            0.05551,
            0.11102
          ],
          "values": [
            [
              0.04479,
              0.10118,
              0.1461,
              0.23249,
              0.40523,
              0.76574
            ],
            [
              0.0448,
              0.1012,
              0.14613,
              0.23183,
              0.40564,
              0.767
            ],
            [
              0.0448,
              0.10129,
              0.1461,
              0.23228,
              0.40545,
              0.76611
            ],
            [
              0.04477,
              0.10128,
              0.14609,
              0.23171,
              0.4056,
              0.76691
            ],
            [
              0.0448,
              0.10128,
              0.14609,
              0.23171,
              0.40561,
              0.76689
            ],
            [
              0.04479,
              0.10113,
              0.14613,
              0.23177,
              0.40557,
              0.76696
            ],
            [
              0.04478,
              0.10118,
              0.14609,
              0.23234,
              0.40512,
              0.76536
            ],
            [
              0.04479,
              0.10121,
              0.14611,
              0.23248,
              0.40534,
              0.76588
            ],
            [
              0.04476,
              0.10122,
              0.14613,
              0.23218,
              0.40541,
              0.7659
            ],
            [
              0.04481,
              0.10117,
              0.14639,
              0.2319,
              0.4057,
              0.7671
            ],
            [
              0.045,
              0.1014,
              0.1462,
              0.232,
              0.4056,
              0.7666
            ],
            [
              0.0491,
              0.1053,
              0.1493,
              0.2337,
              0.4061,
              0.7672
            ],
            [
              0.0549,
              0.1132,
              0.1581,
              0.2414,
              0.4118,
              0.7688
            ]
          ]
        },
        "related_pin": "A",
        "rise_transition delay_template13x6": {
          "index_1": [
            0.01,
            0.01735,
            0.02602,
            0.03903,
            0.05855,
            0.08782,
            0.13172,
            0.19757,
            0.29634,
            0.44449,
            0.6667,
            1.0,
            1.5
          ],
          "index_2": [
            0.0,
            0.00694,
            0.01388,
            0.02775,
            0.05551,
            0.11102
          ],
          "values": [
            [
              0.04342,
              0.12952,
              0.21622,
              0.39644,
              0.76277,
              1.50091
            ],
            [
              0.04336,
              0.12947,
              0.21647,
              0.39636,
              0.76271,
              1.5008
            ],
            [
              0.04339,
              0.12942,
              0.21605,
              0.3963,
              0.76329,
              1.49988
            ],
            [
              0.04339,
              0.1294,
              0.21633,
              0.39618,
              0.7627,
              1.50014
            ],
            [
              0.04338,
              0.12939,
              0.21628,
              0.39615,
              0.76268,
              1.50026
            ],
            [
              0.04338,
              0.12938,
              0.21598,
              0.39619,
              0.76315,
              1.4997
            ],
            [
              0.04336,
              0.1294,
              0.21599,
              0.39617,
              0.7623,
              1.49957
            ],
            [
              0.0434,
              0.12943,
              0.21631,
              0.39605,
              0.76301,
              1.50008
            ],
            [
              0.04378,
              0.12953,
              0.21638,
              0.39565,
              0.76313,
              1.49937
            ],
            [
              0.04643,
              0.13056,
              0.21691,
              0.3963,
              0.7626,
              1.5026
            ],
            [
              0.05027,
              0.13395,
              0.2187,
              0.3966,
              0.7624,
              1.4999
            ],
            [
              0.056,
              0.1383,
              0.2224,
              0.3984,
              0.7643,
              1.5002
            ],
            [
              0.065,
              0.1451,
              0.227,
              0.4017,
              0.7632,
              1.501
            ]
          ]
        },
        "sdf_cond": "(B&!C)",
        "timing_sense": "positive_unate",
        "when": "(B&!C)"
      },
      {
        "cell_fall delay_template13x6": {
          "index_1": [
            0.01,
            0.01735,
            0.02602,
            0.03903,
            0.05855,
            0.08782,
            0.13172,
            0.19757,
            0.29634,
            0.44449,
            0.6667,
            1.0,
            1.5
          ],
          "index_2": [
            0.0,
            0.00694,
            0.01388,
            0.02775,
            0.05551,
            0.11102
          ],
          "values": [
            [
              0.33417,
              0.42486,
              0.48366,
              0.57646,
              0.73229,
              1.01657
            ],
            [
              0.33644,
              0.4272,
              0.486,
              0.57881,
              0.73453,
              1.01894
            ],
            [
              0.3389,
              0.42958,
              0.48838,
              0.5812,
              0.73699,
              1.02132
            ],
            [
              0.3426,
              0.43324,
              0.49206,
              0.58486,
              0.74059,
              1.02497
            ],
            [
              0.34848,
              0.43906,
              0.49785,
              0.59064,
              0.74634,
              1.03041
            ],
            [
              0.35817,
              0.4486,
              0.50741,
              0.60018,
              0.75595,
              1.04032
            ],
            [
              0.374,
              0.46435,
              0.52306,
              0.61584,
              0.77161,
              1.05603
            ],
            [
              0.39981,
              0.48999,
              0.54861,
              0.64138,
              0.79715,
              1.08166
            ],
            [
              0.4411,
              0.53104,
              0.58958,
              0.68228,
              0.83805,
              1.12255
            ],
            [
              0.50605,
              0.59554,
              0.65389,
              0.74659,
              0.90239,
              1.18679
            ],
            [
              0.60612,
              0.69512,
              0.75342,
              0.84612,
              1.00192,
              1.28622
            ],
            [
              0.74167,
              0.83477,
              0.89537,
              0.98967,
              1.14637,
              1.43127
            ],
            [
              0.9125,
              1.0103,
              1.0729,
              1.1727,
              1.3363,
              1.6238
            ]
          ]
        },
        "cell_rise delay_template13x6": {
          "index_1": [
            0.01,
            0.01735,
            0.02602,
            0.03903,
            0.05855,
            0.08782,
            0.13172,
            0.19757,
            0.29634,
            0.44449,
            0.6667,
            1.0,
            1.5
          ],
          "index_2": [
            0.0,
            0.00694,
            0.01388,
            0.02775,
            0.05551,
            0.11102
          ],
          "values": [
            [
              0.1708,
              0.2651,
              0.33655,
              0.47054,
              0.73403,
              1.26197
            ],
            [
              0.17383,
              0.2681,
              0.33962,
              0.47352,
              0.73761,
              1.26534
            ],
            [
              0.17733,
              0.27158,
              0.34311,
              0.47706,
              0.74057,
              1.26882
            ],
            [
              0.18252,
              0.27672,
              0.34814,
              0.48213,
              0.74631,
              1.27228
            ],
            [
              0.19023,
              0.28438,
              0.35591,
              0.48982,
              0.7538,
              1.28081
            ],
            [
              0.20182,
              0.29584,
              0.36732,
              0.50131,
              0.76489,
              1.29242
            ],
            [
              0.21936,
              0.31315,
              0.38456,
              0.51852,
              0.7822,
              1.30973
            ],
            [
              0.24603,
              0.33951,
              0.4109,
              0.54497,
              0.80914,
              1.33636
            ],
            [
              0.28507,
              0.37884,
              0.45023,
              0.58435,
              0.84855,
              1.37515
            ],
            [
              0.33452,
              0.43263,
              0.5045,
              0.63859,
              0.90329,
              1.43029
            ],
            [
              0.39522,
              0.49872,
              0.57292,
              0.70842,
              0.97292,
              1.50052
            ],
            [
              0.46897,
              0.57917,
              0.65487,
              0.79267,
              1.05867,
              1.58597
            ],
            [
              0.5555,
              0.6766,
              0.7549,
              0.8935,
              1.1615,
              1.6891
            ]
          ]
        },
        "fall_transition delay_template13x6": {
          "index_1": [
            0.01,
            0.01735,
            0.02602,
            0.03903,
            0.05855,
            0.08782,
            0.13172,
            0.19757,
            0.29634,
            0.44449,
            0.6667,
            1.0,
            1.5
          ],
          "index_2": [
            0.0,
            0.00694,
            0.01388,
            0.02775,
            0.05551,
            0.11102
          ],
          "values": [
            [
              0.04856,
              0.11569,
              0.16436,
              0.25116,
              0.42176,
              0.77341
            ],
            [
              0.0485,
              0.11556,
              0.1642,
              0.25092,
              0.42202,
              0.77459
            ],
            [
              0.04852,
              0.11578,
              0.16415,
              0.25163,
              0.4221,
              0.77454
            ],
            [
              0.0485,
              0.11556,
              0.1641,
              0.25083,
              0.42174,
              0.77444
            ],
            [
              0.04845,
              0.11551,
              0.16432,
              0.25093,
              0.42191,
              0.77392
            ],
            [
              0.04843,
              0.11549,
              0.164,
              0.2514,
              0.42186,
              0.77444
            ],
            [
              0.04837,
              0.11537,
              0.16383,
              0.25077,
              0.4216,
              0.77435
            ],
            [
              0.04835,
              0.11527,
              0.16396,
              0.25077,
              0.42226,
              0.77405
            ],
            [
              0.04821,
              0.1151,
              0.16368,
              0.25067,
              0.42131,
              0.7742
            ],
            [
              0.04806,
              0.11506,
              0.16377,
              0.25052,
              0.4211,
              0.7743
            ],
            [
              0.0484,
              0.1147,
              0.1635,
              0.2511,
              0.4213,
              0.7739
            ],
            [
              0.0543,
              0.1208,
              0.1692,
              0.2545,
              0.4231,
              0.7749
            ],
            [
              0.0631,
              0.1261,
              0.1777,
              0.268,
              0.4359,
              0.7806
            ]
          ]
        },
        "related_pin": "B",
        "rise_transition delay_template13x6": {
          "index_1": [
            0.01,
            0.01735,
            0.02602,
            0.03903,
            0.05855,
            0.08782,
            0.13172,
            0.19757,
            0.29634,
            0.44449,
            0.6667,
            1.0,
            1.5
          ],
          "index_2": [
            0.0,
            0.00694,
            0.01388,
            0.02775,
            0.05551,
            0.11102
          ],
          "values": [
            [
              0.04608,
              0.13225,
              0.21855,
              0.39692,
              0.7628,
              1.49846
            ],
            [
              0.04609,
              0.13247,
              0.21845,
              0.39672,
              0.76251,
              1.49942
            ],
            [
              0.04604,
              0.13245,
              0.21841,
              0.39685,
              0.76231,
              1.49826
            ],
            [
              0.04608,
              0.13228,
              0.21837,
              0.39666,
              0.7627,
              1.49874
            ],
            [
              0.04604,
              0.13212,
              0.21811,
              0.39664,
              0.76254,
              1.49863
            ],
            [
              0.04596,
              0.1321,
              0.21788,
              0.39664,
              0.76194,
              1.49862
            ],
            [
              0.04589,
              0.13213,
              0.21798,
              0.39645,
              0.76246,
              1.49895
            ],
            [
              0.04585,
              0.13235,
              0.21797,
              0.3966,
              0.76192,
              1.49999
            ],
            [
              0.04716,
              0.13276,
              0.21815,
              0.39654,
              0.76166,
              1.49923
            ],
            [
              0.05158,
              0.13596,
              0.21966,
              0.39642,
              0.76218,
              1.4975
            ],
            [
              0.0566,
              0.14178,
              0.2248,
              0.3996,
              0.7626,
              1.4982
            ],
            [
              0.0651,
              0.1486,
              0.2306,
              0.4043,
              0.7654,
              1.4975
            ],
            [
              0.0781,
              0.1577,
              0.2372,
              0.4084,
              0.7684,
              1.4994
            ]
          ]
        },
        "sdf_cond": "(!A&C)",
        "timing_sense": "positive_unate",
        "when": "(!A&C)"
      },
      {
        "cell_fall delay_template13x6": {
          "index_1": [
            0.01,
            0.01735,
            0.02602,
            0.03903,
            0.05855,
            0.08782,
            0.13172,
            0.19757,
            0.29634,
            0.44449,
            0.6667,
            1.0,
            1.5
          ],
          "index_2": [
            0.0,
            0.00694,
            0.01388,
            0.02775,
            0.05551,
            0.11102
          ],
          "values": [
            [
              0.31054,
              0.41772,
              0.48571,
              0.5884,
              0.7538,
              1.04497
            ],
            [
              0.3121,
              0.41926,
              0.48731,
              0.58995,
              0.75531,
              1.04644
            ],
            [
              0.31399,
              0.42106,
              0.48909,
              0.59173,
              0.75705,
              1.04812
            ],
            [
              0.3171,
              0.42407,
              0.49208,
              0.59469,
              0.76001,
              1.05108
            ],
            [
              0.32248,
              0.42936,
              0.49732,
              0.59994,
              0.76522,
              1.05621
            ],
            [
              0.33184,
              0.43857,
              0.50649,
              0.60908,
              0.77437,
              1.06532
            ],
            [
              0.34764,
              0.45418,
              0.52206,
              0.62459,
              0.78986,
              1.08093
            ],
            [
              0.37366,
              0.47995,
              0.54772,
              0.65025,
              0.81555,
              1.10656
            ],
            [
              0.41541,
              0.52128,
              0.58894,
              0.69146,
              0.85675,
              1.14785
            ],
            [
              0.48097,
              0.58619,
              0.65369,
              0.75619,
              0.92159,
              1.21269
            ],
            [
              0.57972,
              0.68502,
              0.75262,
              0.85542,
              1.02092,
              1.31212
            ],
            [
              0.70747,
              0.81947,
              0.89087,
              0.99617,
              1.16327,
              1.45507
            ],
            [
              0.8686,
              0.9897,
              1.0648,
              1.1773,
              1.3524,
              1.6477
            ]
          ]
        },
        "cell_rise delay_template13x6": {
          "index_1": [
            0.01,
            0.01735,
            0.02602,
            0.03903,
            0.05855,
            0.08782,
            0.13172,
            0.19757,
            0.29634,
            0.44449,
            0.6667,
            1.0,
            1.5
          ],
          "index_2": [
            0.0,
            0.00694,
            0.01388,
            0.02775,
            0.05551,
            0.11102
          ],
          "values": [
            [
              0.18123,
              0.26854,
              0.3378,
              0.47051,
              0.73432,
              1.26027
            ],
            [
              0.18456,
              0.27181,
              0.34114,
              0.47374,
              0.73731,
              1.26424
            ],
            [
              0.18836,
              0.27563,
              0.34487,
              0.47765,
              0.74131,
              1.26742
            ],
            [
              0.19392,
              0.28113,
              0.35041,
              0.48318,
              0.74686,
              1.27268
            ],
            [
              0.20199,
              0.28919,
              0.35846,
              0.49122,
              0.75459,
              1.28131
            ],
            [
              0.21391,
              0.30106,
              0.37041,
              0.50319,
              0.76685,
              1.29222
            ],
            [
              0.23171,
              0.31881,
              0.38823,
              0.52096,
              0.78491,
              1.31003
            ],
            [
              0.25862,
              0.34561,
              0.41503,
              0.54778,
              0.81145,
              1.33696
            ],
            [
              0.29921,
              0.38615,
              0.45559,
              0.58844,
              0.85225,
              1.37825
            ],
            [
              0.35331,
              0.44294,
              0.51268,
              0.64569,
              0.90929,
              1.43679
            ],
            [
              0.41923,
              0.51302,
              0.58472,
              0.71862,
              0.98252,
              1.50822
            ],
            [
              0.49987,
              0.59787,
              0.67067,
              0.80667,
              1.07167,
              1.59837
            ],
            [
              0.596,
              0.7005,
              0.7748,
              0.9111,
              1.1782,
              1.7052
            ]
          ]
        },
        "fall_transition delay_template13x6": {
          "index_1": [
            0.01,
            0.01735,
            0.02602,
            0.03903,
            0.05855,
            0.08782,
            0.13172,
            0.19757,
            0.29634,
            0.44449,
            0.6667,
            1.0,
            1.5
          ],
          "index_2": [
            0.0,
            0.00694,
            0.01388,
            0.02775,
            0.05551,
            0.11102
          ],
          "values": [
            [
              0.05285,
              0.13491,
              0.186,
              0.27354,
              0.44211,
              0.78621
            ],
            [
              0.05283,
              0.13459,
              0.1857,
              0.27345,
              0.44198,
              0.78637
            ],
            [
              0.05276,
              0.13459,
              0.18564,
              0.27338,
              0.44103,
              0.78628
            ],
            [
              0.05277,
              0.13444,
              0.18558,
              0.27274,
              0.44079,
              0.78639
            ],
            [
              0.05274,
              0.13441,
              0.18554,
              0.27326,
              0.44068,
              0.78572
            ],
            [
              0.05266,
              0.13434,
              0.18547,
              0.27264,
              0.44076,
              0.78513
            ],
            [
              0.05263,
              0.1343,
              0.18541,
              0.2725,
              0.44098,
              0.7859
            ],
            [
              0.05258,
              0.13416,
              0.18534,
              0.27253,
              0.44124,
              0.78618
            ],
            [
              0.05242,
              0.13432,
              0.18534,
              0.27313,
              0.44034,
              0.7859
            ],
            [
              0.05231,
              0.13396,
              0.18535,
              0.27242,
              0.4403,
              0.7862
            ],
            [
              0.0545,
              0.1349,
              0.186,
              0.273,
              0.4407,
              0.7854
            ],
            [
              0.0616,
              0.144,
              0.1954,
              0.2793,
              0.4451,
              0.7876
            ],
            [
              0.0724,
              0.1547,
              0.2084,
              0.2967,
              0.4598,
              0.7951
            ]
          ]
        },
        "related_pin": "B",
        "rise_transition delay_template13x6": {
          "index_1": [
            0.01,
            0.01735,
            0.02602,
            0.03903,
            0.05855,
            0.08782,
            0.13172,
            0.19757,
            0.29634,
            0.44449,
            0.6667,
            1.0,
            1.5
          ],
          "index_2": [
            0.0,
            0.00694,
            0.01388,
            0.02775,
            0.05551,
            0.11102
          ],
          "values": [
            [
              0.0416,
              0.12916,
              0.21646,
              0.39644,
              0.76389,
              1.49984
            ],
            [
              0.04158,
              0.12909,
              0.21638,
              0.39647,
              0.76366,
              1.49985
            ],
            [
              0.04156,
              0.12907,
              0.21636,
              0.39641,
              0.76311,
              1.49889
            ],
            [
              0.04153,
              0.129,
              0.21628,
              0.3963,
              0.76321,
              1.49906
            ],
            [
              0.04151,
              0.12901,
              0.21624,
              0.3961,
              0.76252,
              1.49982
            ],
            [
              0.04148,
              0.12892,
              0.21604,
              0.3962,
              0.76297,
              1.5049
            ],
            [
              0.04139,
              0.12889,
              0.21578,
              0.39596,
              0.76252,
              1.49896
            ],
            [
              0.04133,
              0.1289,
              0.21576,
              0.39602,
              0.76335,
              1.49923
            ],
            [
              0.04143,
              0.12892,
              0.21604,
              0.39601,
              0.76251,
              1.50039
            ],
            [
              0.04449,
              0.13045,
              0.21653,
              0.39611,
              0.76313,
              1.4993
            ],
            [
              0.0473,
              0.1354,
              0.2207,
              0.3982,
              0.7625,
              1.4998
            ],
            [
              0.0517,
              0.1397,
              0.2247,
              0.4013,
              0.7653,
              1.4982
            ],
            [
              0.0598,
              0.1456,
              0.2288,
              0.4052,
              0.7672,
              1.4997
            ]
          ]
        },
        "sdf_cond": "(A&!C)",
        "timing_sense": "positive_unate",
        "when": "(A&!C)"
      },
      {
        "cell_fall delay_template13x6": {
          "index_1": [
            0.01,
            0.01735,
            0.02602,
            0.03903,
            0.05855,
            0.08782,
            0.13172,
            0.19757,
            0.29634,
            0.44449,
            0.6667,
            1.0,
            1.5
          ],
          "index_2": [
            0.0,
            0.00694,
            0.01388,
            0.02775,
            0.05551,
            0.11102
          ],
          "values": [
            [
              0.3569,
              0.4368,
              0.4885,
              0.57292,
              0.72108,
              1.00137
            ],
            [
              0.35918,
              0.4391,
              0.4908,
              0.5752,
              0.72334,
              1.00354
            ],
            [
              0.36172,
              0.4416,
              0.49331,
              0.57773,
              0.72579,
              1.00582
            ],
            [
              0.36558,
              0.44546,
              0.49718,
              0.58159,
              0.72972,
              1.00988
            ],
            [
              0.37163,
              0.45149,
              0.50322,
              0.58763,
              0.73575,
              1.01571
            ],
            [
              0.38132,
              0.46112,
              0.51287,
              0.59728,
              0.74539,
              1.02532
            ],
            [
              0.3968,
              0.47658,
              0.52827,
              0.6127,
              0.76081,
              1.04113
            ],
            [
              0.42157,
              0.50133,
              0.55298,
              0.63741,
              0.78555,
              1.06586
            ],
            [
              0.46091,
              0.54058,
              0.59221,
              0.67663,
              0.82475,
              1.10475
            ],
            [
              0.5225,
              0.60207,
              0.65359,
              0.73809,
              0.88619,
              1.16649
            ],
            [
              0.61722,
              0.69672,
              0.74832,
              0.83282,
              0.98112,
              1.26132
            ],
            [
              0.74877,
              0.83247,
              0.88547,
              0.97087,
              1.11967,
              1.40017
            ],
            [
              0.9119,
              1.0028,
              1.0583,
              1.147,
              1.2994,
              1.5816
            ]
          ]
        },
        "cell_rise delay_template13x6": {
          "index_1": [
            0.01,
            0.01735,
            0.02602,
            0.03903,
            0.05855,
            0.08782,
            0.13172,
            0.19757,
            0.29634,
            0.44449,
            0.6667,
            1.0,
            1.5
          ],
          "index_2": [
            0.0,
            0.00694,
            0.01388,
            0.02775,
            0.05551,
            0.11102
          ],
          "values": [
            [
              0.17086,
              0.26481,
              0.33619,
              0.46999,
              0.73418,
              1.26117
            ],
            [
              0.17427,
              0.26817,
              0.33956,
              0.4734,
              0.73739,
              1.26414
            ],
            [
              0.17811,
              0.27199,
              0.34332,
              0.47714,
              0.7412,
              1.26812
            ],
            [
              0.18346,
              0.27735,
              0.3487,
              0.48255,
              0.74645,
              1.27307
            ],
            [
              0.1909,
              0.28472,
              0.35602,
              0.48974,
              0.75385,
              1.28091
            ],
            [
              0.20161,
              0.29533,
              0.36671,
              0.50061,
              0.76453,
              1.29092
            ],
            [
              0.21747,
              0.31101,
              0.38238,
              0.51617,
              0.78034,
              1.30723
            ],
            [
              0.24115,
              0.33443,
              0.40567,
              0.53973,
              0.80375,
              1.33056
            ],
            [
              0.27515,
              0.36896,
              0.44034,
              0.57441,
              0.83865,
              1.36445
            ],
            [
              0.3192,
              0.41709,
              0.48907,
              0.62333,
              0.88759,
              1.41489
            ],
            [
              0.37705,
              0.47872,
              0.55282,
              0.68852,
              0.95282,
              1.47982
            ],
            [
              0.45067,
              0.55727,
              0.63287,
              0.77027,
              1.03607,
              1.56217
            ],
            [
              0.5404,
              0.655,
              0.7329,
              0.8715,
              1.1389,
              1.6669
            ]
          ]
        },
        "fall_transition delay_template13x6": {
          "index_1": [
            0.01,
            0.01735,
            0.02602,
            0.03903,
            0.05855,
            0.08782,
            0.13172,
            0.19757,
            0.29634,
            0.44449,
            0.6667,
            1.0,
            1.5
          ],
          "index_2": [
            0.0,
            0.00694,
            0.01388,
            0.02775,
            0.05551,
            0.11102
          ],
          "values": [
            [
              0.04478,
              0.10117,
              0.14606,
              0.23219,
              0.4056,
              0.76667
            ],
            [
              0.04479,
              0.10115,
              0.14603,
              0.23157,
              0.40559,
              0.76689
            ],
            [
              0.04479,
              0.10129,
              0.14598,
              0.23194,
              0.40572,
              0.76669
            ],
            [
              0.04479,
              0.10113,
              0.14605,
              0.23166,
              0.40557,
              0.76694
            ],
            [
              0.0448,
              0.10111,
              0.14625,
              0.23185,
              0.40562,
              0.76708
            ],
            [
              0.04479,
              0.10114,
              0.14636,
              0.23188,
              0.40567,
              0.76694
            ],
            [
              0.04482,
              0.10115,
              0.14603,
              0.23222,
              0.4052,
              0.76528
            ],
            [
              0.0448,
              0.10118,
              0.14605,
              0.23212,
              0.40532,
              0.76595
            ],
            [
              0.04478,
              0.10117,
              0.14642,
              0.23191,
              0.40561,
              0.76682
            ],
            [
              0.04479,
              0.10142,
              0.14623,
              0.23216,
              0.4055,
              0.7664
            ],
            [
              0.0452,
              0.1017,
              0.1463,
              0.2325,
              0.4056,
              0.7665
            ],
            [
              0.0507,
              0.1064,
              0.1503,
              0.2345,
              0.4065,
              0.7672
            ],
            [
              0.0599,
              0.1144,
              0.1585,
              0.2431,
              0.4141,
              0.7696
            ]
          ]
        },
        "related_pin": "C",
        "rise_transition delay_template13x6": {
          "index_1": [
            0.01,
            0.01735,
            0.02602,
            0.03903,
            0.05855,
            0.08782,
            0.13172,
            0.19757,
            0.29634,
            0.44449,
            0.6667,
            1.0,
            1.5
          ],
          "index_2": [
            0.0,
            0.00694,
            0.01388,
            0.02775,
            0.05551,
            0.11102
          ],
          "values": [
            [
              0.04582,
              0.13204,
              0.21809,
              0.39663,
              0.76279,
              1.49813
            ],
            [
              0.04582,
              0.13224,
              0.21807,
              0.39659,
              0.76249,
              1.49818
            ],
            [
              0.04582,
              0.13207,
              0.21812,
              0.39648,
              0.76247,
              1.4976
            ],
            [
              0.0458,
              0.13195,
              0.21801,
              0.39644,
              0.76225,
              1.49794
            ],
            [
              0.04568,
              0.13204,
              0.21819,
              0.39605,
              0.76205,
              1.49882
            ],
            [
              0.04563,
              0.132,
              0.21794,
              0.39646,
              0.76227,
              1.49767
            ],
            [
              0.04551,
              0.13208,
              0.21797,
              0.39626,
              0.76211,
              1.49982
            ],
            [
              0.0455,
              0.13209,
              0.21824,
              0.39644,
              0.76228,
              1.49928
            ],
            [
              0.047,
              0.13254,
              0.21802,
              0.39661,
              0.76232,
              1.49819
            ],
            [
              0.0496,
              0.13564,
              0.21981,
              0.39713,
              0.76204,
              1.4975
            ],
            [
              0.05265,
              0.14054,
              0.2245,
              0.3994,
              0.763,
              1.4977
            ],
            [
              0.0586,
              0.1457,
              0.2294,
              0.4036,
              0.7657,
              1.499
            ],
            [
              0.0688,
              0.1531,
              0.2353,
              0.4077,
              0.7681,
              1.5004
            ]
          ]
        },
        "sdf_cond": "(!A&B)",
        "timing_sense": "positive_unate",
        "when": "(!A&B)"
      },
      {
        "cell_fall delay_template13x6": {
          "index_1": [
            0.01,
            0.01735,
            0.02602,
            0.03903,
            0.05855,
            0.08782,
            0.13172,
            0.19757,
            0.29634,
            0.44449,
            0.6667,
            1.0,
            1.5
          ],
          "index_2": [
            0.0,
            0.00694,
            0.01388,
            0.02775,
            0.05551,
            0.11102
          ],
          "values": [
            [
              0.3203,
              0.42644,
              0.49483,
              0.59773,
              0.76323,
              1.05437
            ],
            [
              0.32329,
              0.42944,
              0.49783,
              0.60075,
              0.76621,
              1.05734
            ],
            [
              0.32671,
              0.43285,
              0.50124,
              0.60414,
              0.76961,
              1.06072
            ],
            [
              0.33191,
              0.43802,
              0.50641,
              0.60933,
              0.77477,
              1.06588
            ],
            [
              0.33994,
              0.44601,
              0.5144,
              0.61733,
              0.78278,
              1.07381
            ],
            [
              0.35212,
              0.45813,
              0.52651,
              0.62942,
              0.79487,
              1.08602
            ],
            [
              0.37016,
              0.47607,
              0.54439,
              0.64728,
              0.81273,
              1.10373
            ],
            [
              0.39698,
              0.50267,
              0.57091,
              0.67381,
              0.83926,
              1.13036
            ],
            [
              0.43727,
              0.54262,
              0.61079,
              0.71365,
              0.87915,
              1.17025
            ],
            [
              0.49799,
              0.60276,
              0.67079,
              0.77369,
              0.93919,
              1.23039
            ],
            [
              0.58722,
              0.69202,
              0.76022,
              0.86322,
              1.02892,
              1.32002
            ],
            [
              0.70287,
              0.81237,
              0.88427,
              0.98997,
              1.15707,
              1.44887
            ],
            [
              0.8559,
              0.9694,
              1.0442,
              1.1564,
              1.3313,
              1.6266
            ]
          ]
        },
        "cell_rise delay_template13x6": {
          "index_1": [
            0.01,
            0.01735,
            0.02602,
            0.03903,
            0.05855,
            0.08782,
            0.13172,
            0.19757,
            0.29634,
            0.44449,
            0.6667,
            1.0,
            1.5
          ],
          "index_2": [
            0.0,
            0.00694,
            0.01388,
            0.02775,
            0.05551,
            0.11102
          ],
          "values": [
            [
              0.20637,
              0.29197,
              0.36185,
              0.49611,
              0.76132,
              1.29037
            ],
            [
              0.20951,
              0.29501,
              0.36495,
              0.49916,
              0.76439,
              1.29314
            ],
            [
              0.21329,
              0.29874,
              0.36868,
              0.50281,
              0.76819,
              1.29662
            ],
            [
              0.21887,
              0.30436,
              0.37416,
              0.50821,
              0.77338,
              1.30178
            ],
            [
              0.22711,
              0.31256,
              0.38239,
              0.51657,
              0.78141,
              1.31041
            ],
            [
              0.23932,
              0.32473,
              0.39457,
              0.52874,
              0.79343,
              1.32252
            ],
            [
              0.25757,
              0.34299,
              0.41268,
              0.54668,
              0.81193,
              1.33953
            ],
            [
              0.28503,
              0.37037,
              0.43999,
              0.57395,
              0.83946,
              1.36746
            ],
            [
              0.32666,
              0.41173,
              0.48136,
              0.61532,
              0.88095,
              1.40915
            ],
            [
              0.38808,
              0.47334,
              0.54289,
              0.67679,
              0.94239,
              1.46979
            ],
            [
              0.46632,
              0.55452,
              0.62472,
              0.75882,
              1.02422,
              1.55242
            ],
            [
              0.56277,
              0.65457,
              0.72557,
              0.86067,
              1.12617,
              1.65437
            ],
            [
              0.6796,
              0.7776,
              0.8493,
              0.9846,
              1.2514,
              1.7792
            ]
          ]
        },
        "fall_transition delay_template13x6": {
          "index_1": [
            0.01,
            0.01735,
            0.02602,
            0.03903,
            0.05855,
            0.08782,
            0.13172,
            0.19757,
            0.29634,
            0.44449,
            0.6667,
            1.0,
            1.5
          ],
          "index_2": [
            0.0,
            0.00694,
            0.01388,
            0.02775,
            0.05551,
            0.11102
          ],
          "values": [
            [
              0.05255,
              0.13458,
              0.18623,
              0.27344,
              0.44071,
              0.78653
            ],
            [
              0.05254,
              0.13456,
              0.18621,
              0.27396,
              0.44213,
              0.78654
            ],
            [
              0.05254,
              0.13455,
              0.1862,
              0.27337,
              0.441,
              0.78648
            ],
            [
              0.05254,
              0.13453,
              0.18619,
              0.27335,
              0.44119,
              0.78624
            ],
            [
              0.05255,
              0.13451,
              0.18615,
              0.27391,
              0.44122,
              0.78643
            ],
            [
              0.05252,
              0.13447,
              0.18612,
              0.27339,
              0.44136,
              0.7863
            ],
            [
              0.05249,
              0.13421,
              0.18612,
              0.27334,
              0.44064,
              0.78637
            ],
            [
              0.05238,
              0.13412,
              0.18628,
              0.2733,
              0.44164,
              0.78642
            ],
            [
              0.05231,
              0.13393,
              0.18598,
              0.27322,
              0.44112,
              0.7863
            ],
            [
              0.05208,
              0.13384,
              0.1861,
              0.2732,
              0.4406,
              0.7863
            ],
            [
              0.0539,
              0.1344,
              0.1864,
              0.2735,
              0.441,
              0.7863
            ],
            [
              0.0576,
              0.1423,
              0.195,
              0.28,
              0.4441,
              0.7867
            ],
            [
              0.0632,
              0.1482,
              0.2049,
              0.2951,
              0.4585,
              0.795
            ]
          ]
        },
        "related_pin": "C",
        "rise_transition delay_template13x6": {
          "index_1": [
            0.01,
            0.01735,
            0.02602,
            0.03903,
            0.05855,
            0.08782,
            0.13172,
            0.19757,
            0.29634,
            0.44449,
            0.6667,
            1.0,
            1.5
          ],
          "index_2": [
            0.0,
            0.00694,
            0.01388,
            0.02775,
            0.05551,
            0.11102
          ],
          "values": [
            [
              0.03945,
              0.12725,
              0.21575,
              0.39694,
              0.76526,
              1.50043
            ],
            [
              0.03944,
              0.12721,
              0.21556,
              0.39726,
              0.7642,
              1.50246
            ],
            [
              0.03943,
              0.12717,
              0.21545,
              0.39716,
              0.76438,
              1.50239
            ],
            [
              0.03941,
              0.12716,
              0.21563,
              0.39695,
              0.765,
              1.50091
            ],
            [
              0.03942,
              0.12706,
              0.21545,
              0.39674,
              0.76476,
              1.5005
            ],
            [
              0.03937,
              0.1271,
              0.21537,
              0.39683,
              0.76468,
              1.50112
            ],
            [
              0.03944,
              0.12713,
              0.21554,
              0.39654,
              0.76483,
              1.50098
            ],
            [
              0.03936,
              0.12719,
              0.21548,
              0.3965,
              0.76483,
              1.50103
            ],
            [
              0.03935,
              0.12712,
              0.21532,
              0.39662,
              0.76455,
              1.50181
            ],
            [
              0.04036,
              0.12739,
              0.21533,
              0.39659,
              0.76449,
              1.5008
            ],
            [
              0.04372,
              0.1299,
              0.2171,
              0.3971,
              0.7645,
              1.5021
            ],
            [
              0.0487,
              0.1333,
              0.2199,
              0.3986,
              0.7656,
              1.501
            ],
            [
              0.0567,
              0.1383,
              0.2229,
              0.4011,
              0.7661,
              1.5029
            ]
          ]
        },
        "sdf_cond": "(A&!B)",
        "timing_sense": "positive_unate",
        "when": "(A&!B)"
      }
    ]
  }
}