{
  "area": 31.968,
  "cell_footprint": "sdlclkp",
  "cell_leakage_power": 14.87238,
  "clock_gating_integrated_cell": "latch_posedge_precontrol",
  "driver_waveform_fall": "ramp",
  "driver_waveform_rise": "ramp",
  "leakage_power": [
    {
      "value": 17.5294446,
      "when": "!GATE&!SCE&CLK"
    },
    {
      "value": 16.2944662,
      "when": "GATE&!SCE&!CLK"
    },
    {
      "value": 14.7761066,
      "when": "!GATE&SCE&!CLK"
    },
    {
      "value": 13.7937022,
      "when": "!GATE&SCE&CLK"
    },
    {
      "value": 12.4356019,
      "when": "GATE&SCE&!CLK"
    },
    {
      "value": 17.3844814,
      "when": "!GATE&!SCE&!CLK"
    },
    {
      "value": 15.3120361,
      "when": "GATE&!SCE&CLK"
    },
    {
      "value": 11.4532206,
      "when": "GATE&SCE&CLK"
    }
  ],
  "pg_pin VGND": {
    "pg_type": "primary_ground",
    "voltage_name": "VGND"
  },
  "pg_pin VNB": {
    "pg_type": "primary_ground",
    "voltage_name": "VNB"
  },
  "pg_pin VPB": {
    "pg_type": "primary_power",
    "voltage_name": "VPB"
  },
  "pg_pin VPWR": {
    "pg_type": "primary_power",
    "voltage_name": "VPWR"
  },
  "pin CLK": {
    "capacitance": 0.004657,
    "clock": "true",
    "clock_gate_clock_pin": "true",
    "direction": "input",
    "fall_capacitance": 0.004476,
    "internal_power": {
      "fall_power hidden_pwr_template13": {
        "index_1": [
          0.01,
          0.01735,
          0.02602,
          0.03903,
          0.05855,
          0.08782,
          0.13172,
          0.19757,
          0.29634,
          0.44449,
          0.6667,
          1.0,
          1.5
        ],
        "values": [
          0.0220796,
          0.0219291,
          0.0217535,
          0.0217603,
          0.0217754,
          0.021791,
          0.0218194,
          0.0221379,
          0.0226205,
          0.023691,
          0.0253018,
          0.0277229,
          0.03136
        ]
      },
      "rise_power hidden_pwr_template13": {
        "index_1": [
          0.01,
          0.01735,
          0.02602,
          0.03903,
          0.05855,
          0.08782,
          0.13172,
          0.19757,
          0.29634,
          0.44449,
          0.6667,
          1.0,
          1.5
        ],
        "values": [
          0.0078047,
          0.0076438,
          0.0074556,
          0.0073746,
          0.0072577,
          0.0072264,
          0.007184,
          0.0073867,
          0.0076952,
          0.0087441,
          0.0103218,
          0.0126927,
          0.0162538
        ]
      }
    },
    "max_transition": 1.5,
    "min_pulse_width_low": 0.162729,
    "related_ground_pin": "VGND",
    "related_power_pin": "VPWR",
    "rise_capacitance": 0.004839
  },
  "pin GATE": {
    "capacitance": 0.002239,
    "clock": "false",
    "clock_gate_enable_pin": "true",
    "direction": "input",
    "fall_capacitance": 0.002149,
    "internal_power": {
      "fall_power hidden_pwr_template13": {
        "index_1": [
          0.01,
          0.01735,
          0.02602,
          0.03903,
          0.05855,
          0.08782,
          0.13172,
          0.19757,
          0.29634,
          0.44449,
          0.6667,
          1.0,
          1.5
        ],
        "values": [
          0.0264314,
          0.0263305,
          0.026213,
          0.0261525,
          0.0260658,
          0.0261398,
          0.0262547,
          0.0266131,
          0.0271547,
          0.0281637,
          0.0296812,
          0.0319613,
          0.0353859
        ]
      },
      "rise_power hidden_pwr_template13": {
        "index_1": [
          0.01,
          0.01735,
          0.02602,
          0.03903,
          0.05855,
          0.08782,
          0.13172,
          0.19757,
          0.29634,
          0.44449,
          0.6667,
          1.0,
          1.5
        ],
        "values": [
          0.0164954,
          0.0164113,
          0.0163138,
          0.016275,
          0.0162213,
          0.0162085,
          0.016194,
          0.0163723,
          0.0166444,
          0.0175778,
          0.0189825,
          0.0210941,
          0.0242665
        ]
      }
    },
    "max_transition": 1.5,
    "related_ground_pin": "VGND",
    "related_power_pin": "VPWR",
    "rise_capacitance": 0.002329,
    "timing": [
      {
        "fall_constraint vio_10_10_1": {
          "index_1": [
            0.01,
            0.03125,
            0.0625,
            0.125,
            0.25,
            0.5,
            0.75,
            1.0,
            1.25,
            1.5
          ],
          "index_2": [
            0.01,
            0.03125,
            0.0625,
            0.125,
            0.25,
            0.5,
            0.75,
            1.0,
            1.25,
            1.5
          ],
          "values": [
            [
              0.1301738,
              0.1356588,
              0.1450176,
              0.1649557,
              0.2084941,
              0.2809225,
              0.3362611,
              0.3842754,
              0.4274069,
              0.4668763
            ],
            [
              0.1234681,
              0.1289531,
              0.1383119,
              0.15825,
              0.2005677,
              0.2742168,
              0.3295553,
              0.3775697,
              0.4194805,
              0.4589499
            ],
            [
              0.1141094,
              0.1195944,
              0.1289531,
              0.1488913,
              0.1924297,
              0.2648581,
              0.3201966,
              0.368211,
              0.4113424,
              0.4508118
            ],
            [
              0.1014954,
              0.1057598,
              0.1151185,
              0.1362773,
              0.1798157,
              0.2522441,
              0.3075827,
              0.355597,
              0.3987285,
              0.4381979
            ],
            [
              0.0848125,
              0.0902975,
              0.0996563,
              0.1195944,
              0.1631328,
              0.2367819,
              0.2921205,
              0.3401348,
              0.384487,
              0.4239564
            ],
            [
              0.066095,
              0.0715801,
              0.0809388,
              0.1020977,
              0.1456361,
              0.2192852,
              0.2758444,
              0.3250794,
              0.3694316,
              0.4101217
            ],
            [
              0.0571432,
              0.0626283,
              0.071987,
              0.0931458,
              0.137905,
              0.2103333,
              0.2681133,
              0.3173483,
              0.3617005,
              0.4023906
            ],
            [
              0.0530742,
              0.0585592,
              0.067918,
              0.0890768,
              0.1338359,
              0.207485,
              0.265265,
              0.3145,
              0.3588522,
              0.400763
            ],
            [
              0.0526673,
              0.0581523,
              0.0675111,
              0.0886699,
              0.133429,
              0.2070781,
              0.2648581,
              0.3140931,
              0.359666,
              0.4003561
            ],
            [
              0.0547018,
              0.0589661,
              0.0695456,
              0.0907044,
              0.1342428,
              0.2078919,
              0.2656719,
              0.3161276,
              0.3617005,
              0.4036113
            ]
          ]
        },
        "related_pin": "CLK",
        "rise_constraint vio_10_10_1": {
          "index_1": [
            0.01,
            0.03125,
            0.0625,
            0.125,
            0.25,
            0.5,
            0.75,
            1.0,
            1.25,
            1.5
          ],
          "index_2": [
            0.01,
            0.03125,
            0.0625,
            0.125,
            0.25,
            0.5,
            0.75,
            1.0,
            1.25,
            1.5
          ],
          "values": [
            [
              0.1167461,
              0.1234518,
              0.1340312,
              0.1527487,
              0.180418,
              0.2125632,
              0.2349427,
              0.2487773,
              0.2577292,
              0.2642396
            ],
            [
              0.1100404,
              0.1167461,
              0.1261048,
              0.1448223,
              0.1724915,
              0.2058574,
              0.2270163,
              0.2408509,
              0.2498027,
              0.2563132
            ],
            [
              0.0994609,
              0.1061667,
              0.1167461,
              0.1342428,
              0.1619121,
              0.1964987,
              0.2164368,
              0.2302715,
              0.240444,
              0.2457337
            ],
            [
              0.0856263,
              0.092332,
              0.1016908,
              0.1204082,
              0.1468568,
              0.1802227,
              0.2013815,
              0.2139954,
              0.2229473,
              0.2294577
            ],
            [
              0.0738262,
              0.0805319,
              0.0911113,
              0.1098288,
              0.1350566,
              0.1672018,
              0.1859193,
              0.1985332,
              0.2062643,
              0.211554
            ],
            [
              0.0795228,
              0.0862285,
              0.0968079,
              0.1143047,
              0.1395326,
              0.170457,
              0.1879538,
              0.199347,
              0.2070781,
              0.2123678
            ],
            [
              0.094985,
              0.1016908,
              0.1110495,
              0.1297669,
              0.1537741,
              0.1846986,
              0.2021953,
              0.2135885,
              0.2213197,
              0.2253887
            ],
            [
              0.1141094,
              0.1208151,
              0.1301738,
              0.1476706,
              0.1728984,
              0.2026022,
              0.220099,
              0.2327129,
              0.2392233,
              0.244513
            ],
            [
              0.1344544,
              0.1411602,
              0.1505189,
              0.1680156,
              0.1932435,
              0.2229473,
              0.240444,
              0.2518372,
              0.2607891,
              0.2648581
            ],
            [
              0.1572409,
              0.1627259,
              0.1733053,
              0.1908021,
              0.2160299,
              0.244513,
              0.2620098,
              0.2746237,
              0.2811341,
              0.2864238
            ]
          ]
        },
        "sim_opt": "runlvl=5 accurate=1",
        "timing_type": "setup_rising",
        "violation_delay_degrade_pct": 10
      },
      {
        "fall_constraint vio_10_10_1": {
          "index_1": [
            0.01,
            0.03125,
            0.0625,
            0.125,
            0.25,
            0.5,
            0.75,
            1.0,
            1.25,
            1.5
          ],
          "index_2": [
            0.01,
            0.03125,
            0.0625,
            0.125,
            0.25,
            0.5,
            0.75,
            1.0,
            1.25,
            1.5
          ],
          "values": [
            [
              -0.1066426,
              -0.1109069,
              -0.1202656,
              -0.1402038,
              -0.1837422,
              -0.2500671,
              -0.2993021,
              -0.3412129,
              -0.3794616,
              -0.4152689
            ],
            [
              -0.0999368,
              -0.1054219,
              -0.1147806,
              -0.1347187,
              -0.1770365,
              -0.244582,
              -0.2938171,
              -0.3357279,
              -0.3751973,
              -0.4097839
            ],
            [
              -0.0930195,
              -0.0985046,
              -0.1078633,
              -0.1278014,
              -0.1701191,
              -0.2376647,
              -0.2881205,
              -0.331252,
              -0.3707214,
              -0.4053079
            ],
            [
              -0.0816263,
              -0.0871113,
              -0.0964701,
              -0.1176289,
              -0.1599466,
              -0.2287129,
              -0.2803893,
              -0.3247415,
              -0.364211,
              -0.4012389
            ],
            [
              -0.0698262,
              -0.0740905,
              -0.0834492,
              -0.1046081,
              -0.1481465,
              -0.2169128,
              -0.2710306,
              -0.3166035,
              -0.3585143,
              -0.3955423
            ],
            [
              -0.0547708,
              -0.0590352,
              -0.0683939,
              -0.0895527,
              -0.1343119,
              -0.2055195,
              -0.2608581,
              -0.3076517,
              -0.3507832,
              -0.3902526
            ],
            [
              -0.0470397,
              -0.0525247,
              -0.0618835,
              -0.0830423,
              -0.1278014,
              -0.1990091,
              -0.2555684,
              -0.3035827,
              -0.3467142,
              -0.3861836
            ],
            [
              -0.0441914,
              -0.0496764,
              -0.0590352,
              -0.080194,
              -0.1249531,
              -0.1973815,
              -0.2539408,
              -0.3019551,
              -0.3463073,
              -0.3869974
            ],
            [
              -0.0437845,
              -0.0492695,
              -0.0586283,
              -0.0797871,
              -0.1245462,
              -0.1969746,
              -0.2535338,
              -0.3027689,
              -0.3471211,
              -0.3878112
            ],
            [
              -0.045819,
              -0.051304,
              -0.0606628,
              -0.0818216,
              -0.12536,
              -0.1990091,
              -0.2555684,
              -0.3048034,
              -0.3503763,
              -0.3910664
            ]
          ]
        },
        "related_pin": "CLK",
        "rise_constraint vio_10_10_1": {
          "index_1": [
            0.01,
            0.03125,
            0.0625,
            0.125,
            0.25,
            0.5,
            0.75,
            1.0,
            1.25,
            1.5
          ],
          "index_2": [
            0.01,
            0.03125,
            0.0625,
            0.125,
            0.25,
            0.5,
            0.75,
            1.0,
            1.25,
            1.5
          ],
          "values": [
            [
              -0.0541523,
              -0.0608581,
              -0.0714375,
              -0.0889342,
              -0.1153828,
              -0.1450866,
              -0.1613626,
              -0.1715352,
              -0.1768249,
              -0.1796732
            ],
            [
              -0.0486673,
              -0.055373,
              -0.0659525,
              -0.0834492,
              -0.1098978,
              -0.1396016,
              -0.1558776,
              -0.1660501,
              -0.1713398,
              -0.1729674
            ],
            [
              -0.0441914,
              -0.0508971,
              -0.0614766,
              -0.0789733,
              -0.1042012,
              -0.1326842,
              -0.150181,
              -0.1603535,
              -0.1656432,
              -0.1672708
            ],
            [
              -0.0401224,
              -0.0468281,
              -0.0561868,
              -0.0736836,
              -0.0989115,
              -0.1273945,
              -0.1436706,
              -0.1538431,
              -0.1591328,
              -0.1619811
            ],
            [
              -0.0368672,
              -0.0435729,
              -0.0529316,
              -0.0704284,
              -0.0944355,
              -0.1229186,
              -0.1391947,
              -0.1493672,
              -0.1558776,
              -0.1575052
            ],
            [
              -0.037681,
              -0.0443867,
              -0.0549661,
              -0.0712422,
              -0.0952493,
              -0.1237324,
              -0.1400085,
              -0.150181,
              -0.1566914,
              -0.1607604
            ],
            [
              -0.0445983,
              -0.051304,
              -0.0606628,
              -0.0781595,
              -0.1021667,
              -0.129429,
              -0.1457051,
              -0.1558776,
              -0.1636087,
              -0.1676777
            ],
            [
              -0.0527363,
              -0.0594421,
              -0.0688008,
              -0.0862975,
              -0.1103047,
              -0.1375671,
              -0.1538431,
              -0.1652363,
              -0.1717467,
              -0.1770365
            ],
            [
              -0.0633158,
              -0.0700215,
              -0.0793802,
              -0.096877,
              -0.1208841,
              -0.1481465,
              -0.1644225,
              -0.1758157,
              -0.1823262,
              -0.1863952
            ],
            [
              -0.0751159,
              -0.0818216,
              -0.0911803,
              -0.1074564,
              -0.1314635,
              -0.1587259,
              -0.175002,
              -0.1863952,
              -0.1941263,
              -0.1981953
            ]
          ]
        },
        "sim_opt": "runlvl=5 accurate=1",
        "timing_type": "hold_rising",
        "violation_delay_degrade_pct": 10
      }
    ]
  },
  "pin GCLK": {
    "clock_gate_out_pin": "true",
    "direction": "output",
    "internal_power": {
      "fall_power pwr_template13x13": {
        "index_1": [
          0.01,
          0.01735,
          0.02602,
          0.03903,
          0.05855,
          0.08782,
          0.13172,
          0.19757,
          0.29634,
          0.44449,
          0.6667,
          1,
          1.5
        ],
        "index_2": [
          0,
          0.00935,
          0.01402,
          0.02103,
          0.03155,
          0.04733,
          0.071,
          0.1065,
          0.15975,
          0.23963,
          0.35945,
          0.53917,
          0.80876
        ],
        "values": [
          [
            0.024733,
            0.0118444,
            0.0061112,
            -0.0025353,
            -0.0158302,
            -0.0364129,
            -0.0679256,
            -0.1157999,
            -0.1879622,
            -0.2964791,
            -0.4594315,
            -0.7039377,
            -1.0708711
          ],
          [
            0.0246467,
            0.0118189,
            0.0060863,
            -0.0025445,
            -0.0158604,
            -0.0364123,
            -0.0679404,
            -0.1158258,
            -0.1879996,
            -0.2965038,
            -0.4594635,
            -0.7039856,
            -1.0709111
          ],
          [
            0.0247128,
            0.0118608,
            0.006142,
            -0.0025234,
            -0.015803,
            -0.0363753,
            -0.0679449,
            -0.1157916,
            -0.1879638,
            -0.296489,
            -0.4594368,
            -0.70397,
            -1.0708828
          ],
          [
            0.024486,
            0.0116539,
            0.0058918,
            -0.0027069,
            -0.016014,
            -0.0365872,
            -0.0681124,
            -0.1159902,
            -0.1881603,
            -0.2966597,
            -0.4596182,
            -0.7041642,
            -1.0710525
          ],
          [
            0.0243888,
            0.0115131,
            0.005719,
            -0.002853,
            -0.0161527,
            -0.0367207,
            -0.0682644,
            -0.1161279,
            -0.1882925,
            -0.2968032,
            -0.4597508,
            -0.7042799,
            -1.0711691
          ],
          [
            0.0243514,
            0.0114806,
            0.0056813,
            -0.0029234,
            -0.0162448,
            -0.0368235,
            -0.068358,
            -0.1162207,
            -0.1883767,
            -0.2968623,
            -0.459809,
            -0.7043494,
            -1.0712193
          ],
          [
            0.0244594,
            0.0115414,
            0.0057283,
            -0.0029087,
            -0.0162456,
            -0.0368341,
            -0.0683862,
            -0.1162143,
            -0.1883474,
            -0.2968326,
            -0.4597408,
            -0.7042605,
            -1.071143
          ],
          [
            0.0246016,
            0.0115807,
            0.0056923,
            -0.0029746,
            -0.0163657,
            -0.0369869,
            -0.0685205,
            -0.1163497,
            -0.1884572,
            -0.2968931,
            -0.4597918,
            -0.7042966,
            -1.0711728
          ],
          [
            0.0255306,
            0.0121471,
            0.0061824,
            -0.0026324,
            -0.0161423,
            -0.0368464,
            -0.0684247,
            -0.1162463,
            -0.1883333,
            -0.2967595,
            -0.4596259,
            -0.7040688,
            -1.0709381
          ],
          [
            0.0269373,
            0.0130121,
            0.0069328,
            -0.0021127,
            -0.0156799,
            -0.0364784,
            -0.0681382,
            -0.1160274,
            -0.1881308,
            -0.2965482,
            -0.4594022,
            -0.7038529,
            -1.0706759
          ],
          [
            0.0314362,
            0.0161785,
            0.0093102,
            -0.0006677,
            -0.0151199,
            -0.0356162,
            -0.0671689,
            -0.1151429,
            -0.1873,
            -0.2957429,
            -0.4585964,
            -0.7030337,
            -1.0698491
          ],
          [
            0.0366794,
            0.0207014,
            0.0136131,
            0.0034285,
            -0.011383,
            -0.0332029,
            -0.0656351,
            -0.1135812,
            -0.1856004,
            -0.2941333,
            -0.4569939,
            -0.7014266,
            -1.0682547
          ],
          [
            0.0428975,
            0.0261899,
            0.0187812,
            0.0082536,
            -0.0069132,
            -0.0290139,
            -0.0616291,
            -0.1101739,
            -0.1827384,
            -0.2909022,
            -0.453798,
            -0.6982844,
            -1.0651103
          ]
        ]
      },
      "related_pin": "CLK",
      "rise_power pwr_template13x13": {
        "index_1": [
          0.01,
          0.01735,
          0.02602,
          0.03903,
          0.05855,
          0.08782,
          0.13172,
          0.19757,
          0.29634,
          0.44449,
          0.6667,
          1,
          1.5
        ],
        "index_2": [
          0,
          0.00935,
          0.01402,
          0.02103,
          0.03155,
          0.04733,
          0.071,
          0.1065,
          0.15975,
          0.23963,
          0.35945,
          0.53917,
          0.80876
        ],
        "values": [
          [
            0.0277524,
            0.0408139,
            0.0474422,
            0.0572115,
            0.0717894,
            0.0934134,
            0.1256941,
            0.1741162,
            0.24605,
            0.3543354,
            0.5157605,
            0.7580252,
            1.122791
          ],
          [
            0.0279073,
            0.0409154,
            0.0474853,
            0.0572947,
            0.0718876,
            0.0934616,
            0.1258111,
            0.1740605,
            0.2464061,
            0.3549961,
            0.5166697,
            0.7587822,
            1.1226238
          ],
          [
            0.0280006,
            0.0409892,
            0.047592,
            0.0573989,
            0.0719625,
            0.0936556,
            0.1258338,
            0.1743942,
            0.2467419,
            0.3549184,
            0.5162296,
            0.7592923,
            1.1222208
          ],
          [
            0.0277001,
            0.0406809,
            0.0473028,
            0.0571033,
            0.0716672,
            0.0933539,
            0.1255357,
            0.1737434,
            0.2460134,
            0.3542154,
            0.5156275,
            0.7582919,
            1.1217817
          ],
          [
            0.0276677,
            0.0406538,
            0.047246,
            0.0570652,
            0.0716316,
            0.0932191,
            0.1255273,
            0.1737538,
            0.2459275,
            0.3538911,
            0.5152583,
            0.7584933,
            1.1213568
          ],
          [
            0.0275392,
            0.0405136,
            0.0471215,
            0.0568996,
            0.0714442,
            0.0931108,
            0.1252615,
            0.1738464,
            0.2460872,
            0.3543996,
            0.5157925,
            0.7584851,
            1.1215799
          ],
          [
            0.0275964,
            0.0405777,
            0.0471296,
            0.0568987,
            0.0715066,
            0.0931952,
            0.1253785,
            0.1733534,
            0.2456886,
            0.3536887,
            0.5151626,
            0.7583628,
            1.1211101
          ],
          [
            0.0277229,
            0.0405083,
            0.046998,
            0.0567684,
            0.0711379,
            0.0927552,
            0.1248746,
            0.1731759,
            0.2453812,
            0.3534416,
            0.5160713,
            0.7576757,
            1.1206961
          ],
          [
            0.0282477,
            0.0408723,
            0.0474154,
            0.0569177,
            0.0712685,
            0.0927291,
            0.124893,
            0.173086,
            0.2452558,
            0.3533642,
            0.5159323,
            0.7581266,
            1.1209694
          ],
          [
            0.0295019,
            0.0413173,
            0.0476382,
            0.0572526,
            0.0716389,
            0.0929358,
            0.1248278,
            0.1727999,
            0.2449967,
            0.3530839,
            0.5149538,
            0.7580334,
            1.1207159
          ],
          [
            0.0313363,
            0.0430622,
            0.0491923,
            0.0585409,
            0.0722633,
            0.09336,
            0.1254236,
            0.1735217,
            0.2448873,
            0.3530878,
            0.5148211,
            0.7581734,
            1.1210316
          ],
          [
            0.0340591,
            0.0451454,
            0.0512385,
            0.0605372,
            0.0746701,
            0.0958856,
            0.1269374,
            0.174873,
            0.2473797,
            0.3544685,
            0.5158875,
            0.7588597,
            1.1239382
          ],
          [
            0.0386646,
            0.0488738,
            0.0548278,
            0.0641706,
            0.0779983,
            0.0991397,
            0.1310281,
            0.1782191,
            0.2489105,
            0.3572382,
            0.5195659,
            0.7602187,
            1.1244297
          ]
        ]
      }
    },
    "max_capacitance": 0.80876,
    "max_transition": 1.714159,
    "power_down_function": "(!VPWR + VGND)",
    "related_ground_pin": "VGND",
    "related_power_pin": "VPWR",
    "state_function": "(CLK*M0)",
    "timing": {
      "cell_fall delay_template13x13": {
        "index_1": [
          0.01,
          0.01735,
          0.02602,
          0.03903,
          0.05855,
          0.08782,
          0.13172,
          0.19757,
          0.29634,
          0.44449,
          0.6667,
          1,
          1.5
        ],
        "index_2": [
          0,
          0.00935,
          0.01402,
          0.02103,
          0.03155,
          0.04733,
          0.071,
          0.1065,
          0.15975,
          0.23963,
          0.35945,
          0.53917,
          0.80876
        ],
        "values": [
          [
            0.1222624,
            0.1422529,
            0.1497858,
            0.1596645,
            0.1726413,
            0.1897338,
            0.2125801,
            0.2438851,
            0.2880443,
            0.3523788,
            0.4479556,
            0.591322,
            0.8052757
          ],
          [
            0.1246925,
            0.1446863,
            0.1521934,
            0.1620675,
            0.175036,
            0.1921269,
            0.2149798,
            0.2462776,
            0.2905036,
            0.3548677,
            0.4503007,
            0.5935193,
            0.8084914
          ],
          [
            0.1277568,
            0.1477303,
            0.1552544,
            0.1651597,
            0.1781224,
            0.1951653,
            0.2180163,
            0.249339,
            0.2935565,
            0.357968,
            0.4536347,
            0.5968706,
            0.8112127
          ],
          [
            0.1325256,
            0.1524895,
            0.1599997,
            0.1698656,
            0.1828345,
            0.1999327,
            0.2227959,
            0.2540912,
            0.2983283,
            0.3627026,
            0.4581661,
            0.6012954,
            0.8164033
          ],
          [
            0.1398544,
            0.1597991,
            0.1673,
            0.1771694,
            0.1901135,
            0.2071916,
            0.2300685,
            0.2613674,
            0.3056467,
            0.3700649,
            0.4656955,
            0.6082718,
            0.8240156
          ],
          [
            0.1513399,
            0.1712728,
            0.1787648,
            0.1886203,
            0.2015673,
            0.2186586,
            0.2415297,
            0.2728283,
            0.3170863,
            0.3814851,
            0.4770278,
            0.6199354,
            0.8352924
          ],
          [
            0.1687397,
            0.1886647,
            0.1961447,
            0.2059896,
            0.2189066,
            0.2359611,
            0.2588378,
            0.2901461,
            0.3344385,
            0.3988796,
            0.4945473,
            0.6373197,
            0.8528492
          ],
          [
            0.1953291,
            0.2151685,
            0.2226131,
            0.2324131,
            0.245477,
            0.262402,
            0.2852739,
            0.3165823,
            0.3608621,
            0.4252906,
            0.5208777,
            0.6637049,
            0.8792117
          ],
          [
            0.2332079,
            0.2536293,
            0.261148,
            0.2709984,
            0.284064,
            0.3012117,
            0.3240699,
            0.3554159,
            0.3996103,
            0.464016,
            0.5596448,
            0.7029896,
            0.9165429
          ],
          [
            0.2792407,
            0.3016578,
            0.3098483,
            0.3205645,
            0.3344245,
            0.3522775,
            0.3756555,
            0.4073525,
            0.4518853,
            0.5161913,
            0.611748,
            0.7546757,
            0.9694836
          ],
          [
            0.3343993,
            0.3590729,
            0.3681513,
            0.3798466,
            0.394929,
            0.4139412,
            0.4385817,
            0.471493,
            0.5168169,
            0.5815682,
            0.6771292,
            0.8197706,
            1.0342572
          ],
          [
            0.401538,
            0.4285858,
            0.4386074,
            0.4515456,
            0.4680356,
            0.4888475,
            0.5152826,
            0.5495658,
            0.5960268,
            0.6614784,
            0.7574432,
            0.9000398,
            1.1138411
          ],
          [
            0.4844061,
            0.5140557,
            0.5252499,
            0.539338,
            0.5575699,
            0.5806049,
            0.6095046,
            0.6456632,
            0.6939647,
            0.7603689,
            0.8564162,
            0.9991915,
            1.2131733
          ]
        ]
      },
      "cell_rise delay_template13x13": {
        "index_1": [
          0.01,
          0.01735,
          0.02602,
          0.03903,
          0.05855,
          0.08782,
          0.13172,
          0.19757,
          0.29634,
          0.44449,
          0.6667,
          1,
          1.5
        ],
        "index_2": [
          0,
          0.00935,
          0.01402,
          0.02103,
          0.03155,
          0.04733,
          0.071,
          0.1065,
          0.15975,
          0.23963,
          0.35945,
          0.53917,
          0.80876
        ],
        "values": [
          [
            0.1070073,
            0.1316524,
            0.1411169,
            0.1539648,
            0.1715566,
            0.196077,
            0.2312084,
            0.2830133,
            0.3593127,
            0.4734158,
            0.6436084,
            0.9013765,
            1.2844623
          ],
          [
            0.1092453,
            0.1339046,
            0.1433784,
            0.1562124,
            0.1738368,
            0.198369,
            0.2335325,
            0.2847262,
            0.3614645,
            0.4753727,
            0.6475095,
            0.901908,
            1.2849679
          ],
          [
            0.1115778,
            0.1362672,
            0.145686,
            0.1585006,
            0.1761052,
            0.200753,
            0.2357264,
            0.2872516,
            0.3640094,
            0.4778588,
            0.648534,
            0.9044955,
            1.2894561
          ],
          [
            0.1149786,
            0.1396628,
            0.1490817,
            0.1618921,
            0.1795072,
            0.2041436,
            0.2391414,
            0.2906244,
            0.3673985,
            0.4811655,
            0.6519829,
            0.9089535,
            1.2932808
          ],
          [
            0.1199875,
            0.1446616,
            0.1541208,
            0.1669512,
            0.1845472,
            0.2091154,
            0.2442219,
            0.2954895,
            0.372307,
            0.4857612,
            0.6581036,
            0.913341,
            1.2984326
          ],
          [
            0.1273907,
            0.1520526,
            0.1614656,
            0.1742669,
            0.1918196,
            0.2164712,
            0.251459,
            0.3030448,
            0.3797392,
            0.4938799,
            0.6641078,
            0.9196797,
            1.3053217
          ],
          [
            0.1385729,
            0.1631872,
            0.1726117,
            0.185399,
            0.2029743,
            0.2274607,
            0.2626197,
            0.3138938,
            0.3903328,
            0.5050508,
            0.6768325,
            0.9314972,
            1.3168205
          ],
          [
            0.1539198,
            0.1788982,
            0.1884025,
            0.2012989,
            0.2188418,
            0.2432886,
            0.2784476,
            0.3298082,
            0.4062884,
            0.5205459,
            0.6924643,
            0.9468003,
            1.332163
          ],
          [
            0.1725745,
            0.1987258,
            0.2085561,
            0.2217312,
            0.2395315,
            0.2641797,
            0.2993782,
            0.3507196,
            0.4273363,
            0.5414282,
            0.7136425,
            0.9681548,
            1.3536972
          ],
          [
            0.1937737,
            0.2215182,
            0.2317571,
            0.2454677,
            0.2638124,
            0.2889722,
            0.3243349,
            0.3757328,
            0.4524571,
            0.5659333,
            0.7373099,
            0.9932843,
            1.3786737
          ],
          [
            0.216454,
            0.2461866,
            0.2571496,
            0.2716112,
            0.2906109,
            0.3164364,
            0.3522399,
            0.4039186,
            0.4805183,
            0.593992,
            0.7656014,
            1.0216532,
            1.4067848
          ],
          [
            0.2385254,
            0.2707761,
            0.2827997,
            0.2985102,
            0.3186323,
            0.3454018,
            0.3820461,
            0.4338364,
            0.5102466,
            0.6248206,
            0.7956105,
            1.0513022,
            1.4348397
          ],
          [
            0.2574998,
            0.2923812,
            0.3056442,
            0.3230927,
            0.3450962,
            0.3734279,
            0.4114722,
            0.4642396,
            0.5407369,
            0.6548404,
            0.8266661,
            1.0830031,
            1.4647488
          ]
        ]
      },
      "fall_transition delay_template13x13": {
        "index_1": [
          0.01,
          0.01735,
          0.02602,
          0.03903,
          0.05855,
          0.08782,
          0.13172,
          0.19757,
          0.29634,
          0.44449,
          0.6667,
          1,
          1.5
        ],
        "index_2": [
          0,
          0.00935,
          0.01402,
          0.02103,
          0.03155,
          0.04733,
          0.071,
          0.1065,
          0.15975,
          0.23963,
          0.35945,
          0.53917,
          0.80876
        ],
        "values": [
          [
            0.0252586,
            0.0388573,
            0.0446709,
            0.0525391,
            0.0637369,
            0.0794957,
            0.1029902,
            0.1381744,
            0.1924655,
            0.2758761,
            0.4029634,
            0.5976269,
            0.8871596
          ],
          [
            0.0251427,
            0.0388052,
            0.0447006,
            0.0524949,
            0.0636034,
            0.0794966,
            0.1030143,
            0.1378342,
            0.1922222,
            0.2761041,
            0.4035885,
            0.5968119,
            0.8896497
          ],
          [
            0.025169,
            0.038929,
            0.0448403,
            0.0527697,
            0.0639152,
            0.0797589,
            0.1029382,
            0.1381397,
            0.1919701,
            0.2757653,
            0.4036354,
            0.5959251,
            0.8872867
          ],
          [
            0.0251281,
            0.0388615,
            0.044483,
            0.0526154,
            0.0636301,
            0.0795576,
            0.1029825,
            0.1378925,
            0.192076,
            0.2761086,
            0.4037092,
            0.5961053,
            0.8896771
          ],
          [
            0.0251321,
            0.0390394,
            0.0445439,
            0.0527233,
            0.0637246,
            0.079636,
            0.1030085,
            0.1379547,
            0.1920758,
            0.2756154,
            0.4039244,
            0.5951961,
            0.8901946
          ],
          [
            0.0251311,
            0.03898,
            0.0444372,
            0.0526957,
            0.0636816,
            0.0796431,
            0.1029289,
            0.1379866,
            0.1917338,
            0.2761274,
            0.4038657,
            0.5956895,
            0.8895461
          ],
          [
            0.0251233,
            0.0390765,
            0.0446852,
            0.0527007,
            0.0637984,
            0.079617,
            0.1030269,
            0.1378484,
            0.1920269,
            0.2753345,
            0.4038941,
            0.5954404,
            0.8897486
          ],
          [
            0.0251835,
            0.0393141,
            0.0446195,
            0.0526873,
            0.0639385,
            0.079781,
            0.1029223,
            0.138044,
            0.1918456,
            0.2761281,
            0.4038915,
            0.5958827,
            0.8904064
          ],
          [
            0.0282201,
            0.0415728,
            0.046908,
            0.0545024,
            0.0651542,
            0.0807623,
            0.1036995,
            0.1388117,
            0.1926223,
            0.2757092,
            0.4027003,
            0.5979831,
            0.887022
          ],
          [
            0.0343969,
            0.0476741,
            0.052901,
            0.0604293,
            0.07096,
            0.0851056,
            0.1072789,
            0.1416038,
            0.1942602,
            0.2770113,
            0.4042248,
            0.5958875,
            0.8872631
          ],
          [
            0.0415706,
            0.0557088,
            0.0612431,
            0.0691012,
            0.0799455,
            0.093945,
            0.1153845,
            0.1481756,
            0.1986532,
            0.2798797,
            0.4058998,
            0.5973056,
            0.8893669
          ],
          [
            0.0509427,
            0.0657108,
            0.0715592,
            0.0800063,
            0.0900469,
            0.1043652,
            0.1258748,
            0.1566519,
            0.2060462,
            0.2849708,
            0.4077561,
            0.5988943,
            0.889865
          ],
          [
            0.0617572,
            0.0784802,
            0.0844638,
            0.0926173,
            0.1034116,
            0.1183906,
            0.1394459,
            0.1689268,
            0.2158082,
            0.2922438,
            0.4130222,
            0.6007478,
            0.8901404
          ]
        ]
      },
      "related_pin": "CLK",
      "rise_transition delay_template13x13": {
        "index_1": [
          0.01,
          0.01735,
          0.02602,
          0.03903,
          0.05855,
          0.08782,
          0.13172,
          0.19757,
          0.29634,
          0.44449,
          0.6667,
          1,
          1.5
        ],
        "index_2": [
          0,
          0.00935,
          0.01402,
          0.02103,
          0.03155,
          0.04733,
          0.071,
          0.1065,
          0.15975,
          0.23963,
          0.35945,
          0.53917,
          0.80876
        ],
        "values": [
          [
            0.0248952,
            0.0458992,
            0.0551261,
            0.0688047,
            0.0891362,
            0.1200509,
            0.1674215,
            0.2406223,
            0.3515775,
            0.5195872,
            0.7706077,
            1.146252,
            1.7109894
          ],
          [
            0.0249024,
            0.045987,
            0.0551757,
            0.0688995,
            0.0891806,
            0.1199784,
            0.1675198,
            0.2403702,
            0.3516534,
            0.5186906,
            0.7700186,
            1.1474012,
            1.7132838
          ],
          [
            0.0249458,
            0.0460174,
            0.0552267,
            0.0687472,
            0.0891014,
            0.1200791,
            0.1676422,
            0.2403584,
            0.3513362,
            0.518896,
            0.7702208,
            1.1474658,
            1.7133912
          ],
          [
            0.0249462,
            0.0460089,
            0.0552246,
            0.0687269,
            0.0891096,
            0.1200901,
            0.1676132,
            0.2402811,
            0.3511784,
            0.5191601,
            0.7696417,
            1.147898,
            1.7130292
          ],
          [
            0.0249446,
            0.0459992,
            0.0552096,
            0.0688982,
            0.0891477,
            0.1200917,
            0.1672638,
            0.2399254,
            0.3513603,
            0.5181766,
            0.7701818,
            1.147654,
            1.7137697
          ],
          [
            0.0249529,
            0.0459932,
            0.0552396,
            0.0687688,
            0.089127,
            0.1200664,
            0.1676633,
            0.2405799,
            0.3515659,
            0.5187382,
            0.7702331,
            1.1476995,
            1.7137053
          ],
          [
            0.024978,
            0.0460515,
            0.0552125,
            0.0689537,
            0.0892008,
            0.1200198,
            0.1675261,
            0.2406165,
            0.3515378,
            0.5190074,
            0.7705118,
            1.1471978,
            1.7136723
          ],
          [
            0.0261774,
            0.0470526,
            0.0561815,
            0.0696103,
            0.0897462,
            0.1204515,
            0.1674625,
            0.2407453,
            0.351578,
            0.5191871,
            0.7710674,
            1.1471853,
            1.7115573
          ],
          [
            0.0283878,
            0.0495469,
            0.058721,
            0.07203,
            0.0916829,
            0.1220068,
            0.1688005,
            0.2410691,
            0.3518423,
            0.5191256,
            0.7710058,
            1.147116,
            1.7137342
          ],
          [
            0.0315245,
            0.0536039,
            0.0624454,
            0.0753673,
            0.0953282,
            0.1246709,
            0.1713705,
            0.242192,
            0.3518885,
            0.5189321,
            0.7706635,
            1.1476825,
            1.713905
          ],
          [
            0.036082,
            0.0589222,
            0.0679231,
            0.0806978,
            0.0994483,
            0.1286397,
            0.1738941,
            0.2441629,
            0.3526968,
            0.5195512,
            0.7709876,
            1.1483317,
            1.7138019
          ],
          [
            0.0421909,
            0.0662008,
            0.0760483,
            0.0885443,
            0.1068622,
            0.1348428,
            0.1788804,
            0.2477036,
            0.3564648,
            0.5206046,
            0.7714405,
            1.147001,
            1.7141591
          ],
          [
            0.0502941,
            0.0756593,
            0.0864409,
            0.0994226,
            0.1178478,
            0.1444848,
            0.1866817,
            0.2538173,
            0.3583086,
            0.523408,
            0.7721384,
            1.1479441,
            1.7134036
          ]
        ]
      },
      "timing_sense": "positive_unate"
    }
  },
  "pin M0": {
    "direction": "internal",
    "internal_node": "m0",
    "related_ground_pin": "VNB",
    "related_power_pin": "VPWR"
  },
  "pin SCE": {
    "capacitance": 0.002131,
    "clock": "false",
    "clock_gate_test_pin": "true",
    "direction": "input",
    "fall_capacitance": 0.002077,
    "internal_power": {
      "fall_power hidden_pwr_template13": {
        "index_1": [
          0.01,
          0.01735,
          0.02602,
          0.03903,
          0.05855,
          0.08782,
          0.13172,
          0.19757,
          0.29634,
          0.44449,
          0.6667,
          1.0,
          1.5
        ],
        "values": [
          0.0279139,
          0.0278298,
          0.0277319,
          0.027663,
          0.0275633,
          0.0275889,
          0.0276309,
          0.0277975,
          0.028051,
          0.0288139,
          0.0299618,
          0.0316876,
          0.0342802
        ]
      },
      "rise_power hidden_pwr_template13": {
        "index_1": [
          0.01,
          0.01735,
          0.02602,
          0.03903,
          0.05855,
          0.08782,
          0.13172,
          0.19757,
          0.29634,
          0.44449,
          0.6667,
          1.0,
          1.5
        ],
        "values": [
          0.0176183,
          0.0175026,
          0.0173678,
          0.0173363,
          0.0172939,
          0.0172932,
          0.0172969,
          0.0174924,
          0.0177904,
          0.0186727,
          0.0200009,
          0.0219979,
          0.0249985
        ]
      }
    },
    "max_transition": 1.5,
    "related_ground_pin": "VGND",
    "related_power_pin": "VPWR",
    "rise_capacitance": 0.002183,
    "timing": [
      {
        "fall_constraint vio_10_10_1": {
          "index_1": [
            0.01,
            0.03125,
            0.0625,
            0.125,
            0.25,
            0.5,
            0.75,
            1.0,
            1.25,
            1.5
          ],
          "index_2": [
            0.01,
            0.03125,
            0.0625,
            0.125,
            0.25,
            0.5,
            0.75,
            1.0,
            1.25,
            1.5
          ],
          "values": [
            [
              0.1399395,
              0.1466452,
              0.1560039,
              0.1735006,
              0.2084941,
              0.2674948,
              0.3142884,
              0.3561992,
              0.3932272,
              0.4290345
            ],
            [
              0.132013,
              0.1399395,
              0.1480775,
              0.1655742,
              0.2005677,
              0.2595684,
              0.3075827,
              0.3482728,
              0.3865215,
              0.4223288
            ],
            [
              0.123875,
              0.1305807,
              0.1399395,
              0.1574362,
              0.1924297,
              0.2514303,
              0.298224,
              0.3401348,
              0.3771628,
              0.4129701
            ],
            [
              0.1100404,
              0.1167461,
              0.1261048,
              0.1436016,
              0.1785951,
              0.2375957,
              0.28561,
              0.3275208,
              0.3657695,
              0.4003561
            ],
            [
              0.0945781,
              0.1012839,
              0.1094219,
              0.1269186,
              0.1619121,
              0.2221335,
              0.2713685,
              0.3132793,
              0.351528,
              0.3861146
            ],
            [
              0.0758607,
              0.0825664,
              0.0919251,
              0.1094219,
              0.1444154,
              0.2058574,
              0.2550924,
              0.2970032,
              0.3364726,
              0.3735007
            ],
            [
              0.0656882,
              0.0736146,
              0.0829733,
              0.1004701,
              0.1366842,
              0.1981263,
              0.2473613,
              0.2904928,
              0.3299622,
              0.3657695
            ],
            [
              0.0616191,
              0.0695456,
              0.0789043,
              0.096401,
              0.1326152,
              0.1940573,
              0.244513,
              0.2876445,
              0.3271139,
              0.3641419
            ],
            [
              0.0612122,
              0.0691387,
              0.0784974,
              0.0959941,
              0.1309876,
              0.1936504,
              0.2441061,
              0.2872376,
              0.3279277,
              0.3649557
            ],
            [
              0.0632467,
              0.0699525,
              0.0793112,
              0.0980286,
              0.1330221,
              0.1956849,
              0.2461406,
              0.2892721,
              0.3299622,
              0.3669902
            ]
          ]
        },
        "related_pin": "CLK",
        "rise_constraint vio_10_10_1": {
          "index_1": [
            0.01,
            0.03125,
            0.0625,
            0.125,
            0.25,
            0.5,
            0.75,
            1.0,
            1.25,
            1.5
          ],
          "index_2": [
            0.01,
            0.03125,
            0.0625,
            0.125,
            0.25,
            0.5,
            0.75,
            1.0,
            1.25,
            1.5
          ],
          "values": [
            [
              0.1240703,
              0.130776,
              0.1401348,
              0.1612936,
              0.192625,
              0.2333151,
              0.2593568,
              0.2792949,
              0.2931296,
              0.3045228
            ],
            [
              0.1173646,
              0.1228496,
              0.133429,
              0.1533672,
              0.1846986,
              0.2253887,
              0.252651,
              0.2713685,
              0.2864238,
              0.2978171
            ],
            [
              0.1067852,
              0.1134909,
              0.1228496,
              0.1440085,
              0.1753398,
              0.2160299,
              0.2420716,
              0.2620098,
              0.2758444,
              0.2872376
            ],
            [
              0.0929505,
              0.0996563,
              0.109015,
              0.1289531,
              0.1602845,
              0.2009746,
              0.2270163,
              0.2457337,
              0.2595684,
              0.2697409
            ],
            [
              0.0811504,
              0.0878561,
              0.0972148,
              0.117153,
              0.1484844,
              0.1867331,
              0.211554,
              0.2290508,
              0.2428854,
              0.253058
            ],
            [
              0.086847,
              0.0935527,
              0.1029115,
              0.1228496,
              0.1529603,
              0.1899883,
              0.2135885,
              0.2310853,
              0.2436992,
              0.2538717
            ],
            [
              0.1023092,
              0.109015,
              0.1183737,
              0.1383119,
              0.1672018,
              0.2054505,
              0.2290508,
              0.2453268,
              0.2579408,
              0.2681133
            ],
            [
              0.1214336,
              0.1269186,
              0.137498,
              0.1562155,
              0.1863262,
              0.2221335,
              0.2457337,
              0.2632305,
              0.2758444,
              0.2860169
            ],
            [
              0.1417786,
              0.1484844,
              0.1578431,
              0.1765605,
              0.2066712,
              0.2424785,
              0.2660788,
              0.2835755,
              0.2961895,
              0.306362
            ],
            [
              0.1633444,
              0.1700501,
              0.1794089,
              0.199347,
              0.228237,
              0.265265,
              0.2876445,
              0.3051413,
              0.3177552,
              0.3279277
            ]
          ]
        },
        "sim_opt": "runlvl=5 accurate=1",
        "timing_type": "setup_rising",
        "violation_delay_degrade_pct": 10
      },
      {
        "fall_constraint vio_10_10_1": {
          "index_1": [
            0.01,
            0.03125,
            0.0625,
            0.125,
            0.25,
            0.5,
            0.75,
            1.0,
            1.25,
            1.5
          ],
          "index_2": [
            0.01,
            0.03125,
            0.0625,
            0.125,
            0.25,
            0.5,
            0.75,
            1.0,
            1.25,
            1.5
          ],
          "values": [
            [
              -0.1151875,
              -0.1218932,
              -0.131252,
              -0.1487487,
              -0.1825215,
              -0.2366393,
              -0.2797708,
              -0.3180195,
              -0.3513854,
              -0.3835306
            ],
            [
              -0.1097025,
              -0.1164082,
              -0.1257669,
              -0.1432637,
              -0.1770365,
              -0.2311543,
              -0.2742858,
              -0.3125345,
              -0.3459004,
              -0.3780456
            ],
            [
              -0.1027852,
              -0.1094909,
              -0.1176289,
              -0.1351257,
              -0.1701191,
              -0.224237,
              -0.2685892,
              -0.3068379,
              -0.3414245,
              -0.372349
            ],
            [
              -0.0913919,
              -0.0980977,
              -0.1074564,
              -0.1249531,
              -0.1587259,
              -0.2152852,
              -0.2596374,
              -0.2991068,
              -0.3349141,
              -0.3670593
            ],
            [
              -0.0783711,
              -0.0850768,
              -0.0944355,
              -0.1119323,
              -0.1469258,
              -0.2047057,
              -0.2502786,
              -0.2909688,
              -0.326776,
              -0.3613626
            ],
            [
              -0.0633158,
              -0.0700215,
              -0.0793802,
              -0.096877,
              -0.1330911,
              -0.1920918,
              -0.2401061,
              -0.2820169,
              -0.3190449,
              -0.3536315
            ],
            [
              -0.0555846,
              -0.0635111,
              -0.0728698,
              -0.0903665,
              -0.1265807,
              -0.1868021,
              -0.2348164,
              -0.2779479,
              -0.3161966,
              -0.3507832
            ],
            [
              -0.0527363,
              -0.0606628,
              -0.0700215,
              -0.0875182,
              -0.1225117,
              -0.1839538,
              -0.2331888,
              -0.2763203,
              -0.314569,
              -0.351597
            ],
            [
              -0.0523294,
              -0.0602559,
              -0.0696146,
              -0.0871113,
              -0.1233255,
              -0.1847676,
              -0.2340026,
              -0.2771341,
              -0.3166035,
              -0.3524108
            ],
            [
              -0.0555846,
              -0.0622904,
              -0.0716491,
              -0.0891458,
              -0.12536,
              -0.1868021,
              -0.2360371,
              -0.2791686,
              -0.318638,
              -0.355666
            ]
          ]
        },
        "related_pin": "CLK",
        "rise_constraint vio_10_10_1": {
          "index_1": [
            0.01,
            0.03125,
            0.0625,
            0.125,
            0.25,
            0.5,
            0.75,
            1.0,
            1.25,
            1.5
          ],
          "index_2": [
            0.01,
            0.03125,
            0.0625,
            0.125,
            0.25,
            0.5,
            0.75,
            1.0,
            1.25,
            1.5
          ],
          "values": [
            [
              -0.0614766,
              -0.0681823,
              -0.077541,
              -0.0974792,
              -0.1288105,
              -0.1646178,
              -0.1882181,
              -0.2032734,
              -0.2146667,
              -0.2223978
            ],
            [
              -0.0559915,
              -0.0626973,
              -0.072056,
              -0.0919941,
              -0.1233255,
              -0.1591328,
              -0.1815124,
              -0.1977884,
              -0.2091816,
              -0.2169128
            ],
            [
              -0.0515156,
              -0.0582214,
              -0.0675801,
              -0.0875182,
              -0.1176289,
              -0.1534362,
              -0.1758158,
              -0.1920918,
              -0.203485,
              -0.2112161
            ],
            [
              -0.0462259,
              -0.0529316,
              -0.0635111,
              -0.0822285,
              -0.1123392,
              -0.1469258,
              -0.1693053,
              -0.1855814,
              -0.1969746,
              -0.2047057
            ],
            [
              -0.0429707,
              -0.0496764,
              -0.0602559,
              -0.0789733,
              -0.1078633,
              -0.1424499,
              -0.1660501,
              -0.1811055,
              -0.1924987,
              -0.2014505
            ],
            [
              -0.0450052,
              -0.0517109,
              -0.0610697,
              -0.0810078,
              -0.1086771,
              -0.1432637,
              -0.1656432,
              -0.1819193,
              -0.1945332,
              -0.203485
            ],
            [
              -0.0519225,
              -0.0586283,
              -0.067987,
              -0.0867044,
              -0.1143737,
              -0.1489603,
              -0.1713398,
              -0.1876159,
              -0.2002298,
              -0.2091816
            ],
            [
              -0.0600605,
              -0.0667663,
              -0.076125,
              -0.0948425,
              -0.1237324,
              -0.1570983,
              -0.1806986,
              -0.1957539,
              -0.2083678,
              -0.2173197
            ],
            [
              -0.07064,
              -0.0773457,
              -0.0867044,
              -0.1054219,
              -0.1330911,
              -0.1676777,
              -0.1900573,
              -0.2063333,
              -0.2189473,
              -0.2278991
            ],
            [
              -0.0824401,
              -0.0891458,
              -0.0985046,
              -0.117222,
              -0.1448913,
              -0.1794779,
              -0.2006367,
              -0.2169128,
              -0.2295267,
              -0.2384785
            ]
          ]
        },
        "sim_opt": "runlvl=5 accurate=1",
        "timing_type": "hold_rising",
        "violation_delay_degrade_pct": 10
      }
    ]
  },
  "statetable \"CLK GATE SCE\",\"M0\"": {
    "table": "L L L : - : L ,L L H : - : H ,L H L : - : H ,L H H : - : H ,H - - : - : N"
  }
}